{
  "mainQuestId": 20104,
  "title": "酒庄大扫除之二",
  "description": "在女仆长爱德琳的安排下，女仆摩可和海莉也开始了打扫，但是，她们似乎遇见了一点麻烦…",
  "titleTextMapHash": 1518501975,
  "descTextMapHash": 3333074206,
  "mainQuestExcel": {
    "mainQuestId": 20104,
    "titleTextMapHash": 1518501975,
    "title": "酒庄大扫除之二",
    "descTextMapHash": 3333074206,
    "description": "在女仆长爱德琳的安排下，女仆摩可和海莉也开始了打扫，但是，她们似乎遇见了一点麻烦…",
    "chapterId": 0,
    "mainQuestTag": "MAINQUEST_TAG_NONE",
    "activeMode": "PLAY_MODE_ALL",
    "activityId": 0,
    "luaPath": "Actor/Quest/IQ20104",
    "mainQuestRaw": {
      "activeMode": "PLAY_MODE_ALL",
      "activityId": 0,
      "chapterId": 0,
      "descTextMapHash": 3333074206,
      "EPJHBBICPCA": false,
      "FFOAGHNMJKJ": 0,
      "FNFALGGACGA": "",
      "FOKHPBAGMPB": "",
      "GMENNHMBBOH": [
        {
          "actionType": "NONE",
          "id": 0
        },
        {
          "actionType": "NONE",
          "id": 0
        },
        {
          "actionType": "NONE",
          "id": 0
        },
        {
          "actionType": "NONE",
          "id": 0
        },
        {
          "actionType": "NONE",
          "id": 0
        },
        {
          "actionType": "NONE",
          "id": 0
        },
        {
          "actionType": "NONE",
          "id": 0
        },
        {
          "actionType": "NONE",
          "id": 0
        }
      ],
      "id": 20104,
      "IELNANBAMLH": "QUEST_PAUSE_RES_DESTROY_NONE",
      "IGHALKGCHAB": 209400489,
      "LEFIHLHODBM": [],
      "luaPath": "Actor/Quest/IQ20104",
      "mainQuestTag": "MAINQUEST_TAG_NONE",
      "MHHFFHCLDKI": false,
      "PEDANLIDLGE": 0,
      "PEFIFLDHPEE": false,
      "recommendLevel": 0,
      "repeatable": true,
      "resId": 0,
      "rewardIdList": [],
      "series": 0,
      "showRedPoint": false,
      "showType": "QUEST_SHOW",
      "specialShowCondIdList": [],
      "specialShowQuestId": 0,
      "specialShowRewardId": [],
      "suggestTrackMainQuestList": [],
      "suggestTrackOutOfOrder": false,
      "taskID": 24200,
      "titleTextMapHash": 1518501975,
      "type": "IQ",
      "unlockDescTextMapHash": 2246753006
    }
  },
  "flow": [
    {
      "subQuestId": 2010401,
      "order": 1,
      "stepDescription": "与摩可和海莉对话",
      "stepDescTextMapHash": 3332217804,
      "finishConds": [
        {
          "BFGALAINLMD": 0,
          "LNHLPKELCAL": [
            2010401,
            0
          ],
          "PAINLIBBLDK": "QUEST_CONTENT_COMPLETE_TALK",
          "PPFLKMOMKAI": ""
        }
      ],
      "guide": {
        "BEALNDJFMMC": "QUEST_GUIDE_IN_SCENE_STYLE_NONE",
        "BJKFMDGPIBN": "QUEST_GUIDE_INDICATOR_STYLE_NONE",
        "CCLPMCLNLBJ": "NONE",
        "CJHEDKCIHPA": 0,
        "EMAIGPLHEJH": "QUEST_GUIDE_LAYER_SCENE",
        "GGJOHCAJAPP": 0,
        "HFNCMGLBNGO": "",
        "IDLNFDCEJLG": "QUEST_GUIDE_AREA_STYLE_DEFAULT",
        "KCFINIEBBBG": 0,
        "KEDGDANLBHP": "",
        "KNMAMMFJAOB": "QUEST_GUIDE_STYLE_START",
        "LNHLPKELCAL": [
          "1596"
        ],
        "NOCCOBOFKHP": 3,
        "OFEBJNGBEPL": "QUEST_GUIDE_AUTO_NONE",
        "PAINLIBBLDK": "QUEST_GUIDE_NPC"
      },
      "isHidden": false,
      "talkIds": [
        2010401
      ],
      "talks": [
        {
          "talkId": 2010401,
          "talkConfig": {
            "checkActionAfter": false,
            "crowdLOD0List": [],
            "decoratorID": 0,
            "disableTalkReview": false,
            "dontBlockDaily": false,
            "enableCameraDisplacement": false,
            "extraLoadMarkId": [],
            "finishExec": [
              {
                "param": [
                  "",
                  "",
                  "",
                  "",
                  ""
                ],
                "type": "TALK_EXEC_NONE"
              },
              {
                "param": [
                  "",
                  "",
                  "",
                  "",
                  ""
                ],
                "type": "TALK_EXEC_NONE"
              },
              {
                "param": [
                  "",
                  "",
                  "",
                  "",
                  ""
                ],
                "type": "TALK_EXEC_NONE"
              },
              {
                "param": [
                  "",
                  "",
                  "",
                  "",
                  ""
                ],
                "type": "TALK_EXEC_NONE"
              },
              {
                "param": [
                  "",
                  "",
                  "",
                  "",
                  ""
                ],
                "type": "TALK_EXEC_NONE"
              }
            ],
            "forceNpcNotDestroy": false,
            "heroRuleId": 0,
            "ignoreDragonTalkRule": false,
            "isEnableNoBlackInter": false,
            "linkBehaviorGrpId": 0,
            "loadType": "TALK_NORMAL_QUEST",
            "lockGameTime": false,
            "lowPriority": false,
            "newTalkFinishTime": false,
            "onlyQuestNpc": false,
            "participantId": [],
            "prePerformCfg": "",
            "questIdleTalk": false,
            "randomTalkPos": 0,
            "randomTalkPriorityList": [],
            "removeDuplicatedRandomTalk": false,
            "stayFreeStyle": false,
            "talkMarkHideList": [],
            "talkMarkType": "TALK_MARK_NONE",
            "activeMode": "PLAY_MODE_ALL",
            "beginCond": [
              {
                "param": [
                  "2010401",
                  "2",
                  "",
                  "",
                  ""
                ],
                "type": "QUEST_COND_STATE_EQUAL"
              },
              {
                "param": [
                  "",
                  "",
                  "",
                  "",
                  ""
                ],
                "type": "QUEST_COND_NONE"
              },
              {
                "param": [
                  "",
                  "",
                  "",
                  "",
                  ""
                ],
                "type": "QUEST_COND_NONE"
              },
              {
                "param": [
                  "",
                  "",
                  "",
                  "",
                  ""
                ],
                "type": "QUEST_COND_NONE"
              },
              {
                "param": [
                  "",
                  "",
                  "",
                  "",
                  ""
                ],
                "type": "QUEST_COND_NONE"
              },
              {
                "param": [
                  "",
                  "",
                  "",
                  "",
                  ""
                ],
                "type": "QUEST_COND_NONE"
              },
              {
                "param": [
                  "",
                  "",
                  "",
                  "",
                  ""
                ],
                "type": "QUEST_COND_NONE"
              },
              {
                "param": [
                  "",
                  "",
                  "",
                  "",
                  ""
                ],
                "type": "QUEST_COND_NONE"
              },
              {
                "param": [
                  "",
                  "",
                  "",
                  "",
                  ""
                ],
                "type": "QUEST_COND_NONE"
              },
              {
                "param": [
                  "",
                  "",
                  "",
                  "",
                  ""
                ],
                "type": "QUEST_COND_NONE"
              }
            ],
            "beginCondComb": "LOGIC_NONE",
            "beginWay": "TALK_BEGIN_MANUAL",
            "heroTalk": "TALK_HERO_MAIN",
            "id": 2010401,
            "initDialog": 201040101,
            "nextRandomTalks": [],
            "nextTalks": [],
            "npcId": [
              1596
            ],
            "performCfg": "",
            "priority": 0,
            "questId": 20104,
            "showRandomTalkCount": 0
          },
          "dialogs": [
            {
              "nodeId": 201040101,
              "roleType": "TALK_ROLE_NPC",
              "speakerId": 1596,
              "speakerName": "摩可",
              "textMapHash": 3651866010,
              "text": "怎么办…",
              "nextNodeIds": [
                201040102
              ]
            },
            {
              "nodeId": 201040102,
              "roleType": "TALK_ROLE_NPC",
              "speakerId": 1595,
              "speakerName": "海莉",
              "textMapHash": 1451248082,
              "text": "又要挨女仆长骂了…",
              "nextNodeIds": [
                201040103
              ]
            },
            {
              "nodeId": 201040103,
              "roleType": "TALK_ROLE_PLAYER",
              "speakerId": null,
              "speakerName": "旅行者",
              "textMapHash": 3630074858,
              "text": "怎么了？",
              "nextNodeIds": [
                201040104
              ]
            },
            {
              "nodeId": 201040104,
              "roleType": "TALK_ROLE_NPC",
              "speakerId": 1596,
              "speakerName": "摩可",
              "textMapHash": 424875682,
              "text": "爱德琳小姐本来是让我们打扫酒庄的外围…",
              "nextNodeIds": [
                201040105
              ]
            },
            {
              "nodeId": 201040105,
              "roleType": "TALK_ROLE_NPC",
              "speakerId": 1595,
              "speakerName": "海莉",
              "textMapHash": 693528234,
              "text": "其他的地方还好，但是，周围还有很多堆起来的草垛。",
              "nextNodeIds": [
                201040106
              ]
            },
            {
              "nodeId": 201040106,
              "roleType": "TALK_ROLE_NPC",
              "speakerId": 1596,
              "speakerName": "摩可",
              "textMapHash": 3178843314,
              "text": "这些是康纳先生特意堆在这，说是有用处的…",
              "nextNodeIds": [
                201040107
              ]
            },
            {
              "nodeId": 201040107,
              "roleType": "TALK_ROLE_NPC",
              "speakerId": 1595,
              "speakerName": "海莉",
              "textMapHash": 4062929746,
              "text": "虽然因为捆得很牢，暴风的时候这些草垛没有被吹走，但是，有很多落叶被吹到了草垛里面…",
              "nextNodeIds": [
                201040108
              ]
            },
            {
              "nodeId": 201040108,
              "roleType": "TALK_ROLE_NPC",
              "speakerId": 1596,
              "speakerName": "摩可",
              "textMapHash": 2817431354,
              "text": "我们费了好大的劲，也没有把落叶从草垛里清理干净。",
              "nextNodeIds": [
                201040109
              ]
            },
            {
              "nodeId": 201040109,
              "roleType": "TALK_ROLE_NPC",
              "speakerId": 1595,
              "speakerName": "海莉",
              "textMapHash": 2202368898,
              "text": "再这么耗下去，女仆长非得骂我们不可，这可怎么办啊…",
              "nextNodeIds": [
                201040110,
                201040112
              ]
            },
            {
              "nodeId": 201040110,
              "roleType": "TALK_ROLE_PLAYER",
              "speakerId": null,
              "speakerName": "旅行者",
              "textMapHash": 1637943730,
              "text": "交给我吧。",
              "nextNodeIds": [
                201040111
              ]
            },
            {
              "nodeId": 201040111,
              "roleType": "TALK_ROLE_NPC",
              "speakerId": 1596,
              "speakerName": "摩可",
              "textMapHash": 565143010,
              "text": "咦？可以交给你吗！太好了，那就拜托你了！",
              "nextNodeIds": []
            },
            {
              "nodeId": 201040112,
              "roleType": "TALK_ROLE_PLAYER",
              "speakerId": null,
              "speakerName": "旅行者",
              "textMapHash": 1501059146,
              "text": "很难清理吗？",
              "nextNodeIds": [
                201040113
              ]
            },
            {
              "nodeId": 201040113,
              "roleType": "TALK_ROLE_NPC",
              "speakerId": 1595,
              "speakerName": "海莉",
              "textMapHash": 404868522,
              "text": "落叶和草垛都搅一起了，我们只能用手慢慢地分开，实在是太慢了…",
              "nextNodeIds": [
                201040114
              ]
            },
            {
              "nodeId": 201040114,
              "roleType": "TALK_ROLE_NPC",
              "speakerId": 1595,
              "speakerName": "海莉",
              "textMapHash": 1836290074,
              "text": "如果你有什么好办法，就请帮帮我们吧。",
              "nextNodeIds": []
            }
          ]
        }
      ],
      "conditions": {
        "finishCond": [
          {
            "BFGALAINLMD": 0,
            "LNHLPKELCAL": [
              2010401,
              0
            ],
            "PAINLIBBLDK": "QUEST_CONTENT_COMPLETE_TALK",
            "PPFLKMOMKAI": ""
          }
        ],
        "triggerCond": [],
        "execActions": [
          {
            "LNHLPKELCAL": [
              "3",
              "133002905,2"
            ],
            "PAINLIBBLDK": "QUEST_EXEC_REFRESH_GROUP_SUITE"
          },
          {
            "LNHLPKELCAL": [
              "3",
              "133002906,2"
            ],
            "PAINLIBBLDK": "QUEST_EXEC_REFRESH_GROUP_SUITE"
          }
        ],
        "guide": {
          "BEALNDJFMMC": "QUEST_GUIDE_IN_SCENE_STYLE_NONE",
          "BJKFMDGPIBN": "QUEST_GUIDE_INDICATOR_STYLE_NONE",
          "CCLPMCLNLBJ": "NONE",
          "CJHEDKCIHPA": 0,
          "EMAIGPLHEJH": "QUEST_GUIDE_LAYER_SCENE",
          "GGJOHCAJAPP": 0,
          "HFNCMGLBNGO": "",
          "IDLNFDCEJLG": "QUEST_GUIDE_AREA_STYLE_DEFAULT",
          "KCFINIEBBBG": 0,
          "KEDGDANLBHP": "",
          "KNMAMMFJAOB": "QUEST_GUIDE_STYLE_START",
          "LNHLPKELCAL": [
            "1596"
          ],
          "NOCCOBOFKHP": 3,
          "OFEBJNGBEPL": "QUEST_GUIDE_AUTO_NONE",
          "PAINLIBBLDK": "QUEST_GUIDE_NPC"
        }
      }
    },
    {
      "subQuestId": 2010402,
      "order": 2,
      "stepDescription": "扫清落叶堆",
      "stepDescTextMapHash": 3573524292,
      "finishConds": [
        {
          "BFGALAINLMD": 5,
          "LNHLPKELCAL": [
            2010402,
            0
          ],
          "PAINLIBBLDK": "QUEST_CONTENT_LUA_NOTIFY",
          "PPFLKMOMKAI": "1330029061"
        }
      ],
      "guide": {
        "BEALNDJFMMC": "QUEST_GUIDE_IN_SCENE_STYLE_NONE",
        "BJKFMDGPIBN": "QUEST_GUIDE_INDICATOR_STYLE_NONE",
        "CCLPMCLNLBJ": "NONE",
        "CJHEDKCIHPA": 0,
        "EMAIGPLHEJH": "QUEST_GUIDE_LAYER_SCENE",
        "GGJOHCAJAPP": 0,
        "HFNCMGLBNGO": "",
        "IDLNFDCEJLG": "QUEST_GUIDE_AREA_STYLE_DEFAULT",
        "KCFINIEBBBG": 0,
        "KEDGDANLBHP": "",
        "KNMAMMFJAOB": "QUEST_GUIDE_STYLE_POINT",
        "LNHLPKELCAL": [
          "Q20104Target",
          "30"
        ],
        "NOCCOBOFKHP": 3,
        "OFEBJNGBEPL": "QUEST_GUIDE_AUTO_NONE",
        "PAINLIBBLDK": "QUEST_GUIDE_LOCATION"
      },
      "isHidden": false,
      "talkIds": [
        2010402,
        2010405,
        2010406
      ],
      "talks": [
        {
          "talkId": 2010402,
          "talkConfig": {
            "checkActionAfter": false,
            "crowdLOD0List": [],
            "decoratorID": 0,
            "disableTalkReview": false,
            "dontBlockDaily": false,
            "enableCameraDisplacement": false,
            "extraLoadMarkId": [],
            "finishExec": [
              {
                "param": [
                  "",
                  "",
                  "",
                  "",
                  ""
                ],
                "type": "TALK_EXEC_NONE"
              },
              {
                "param": [
                  "",
                  "",
                  "",
                  "",
                  ""
                ],
                "type": "TALK_EXEC_NONE"
              },
              {
                "param": [
                  "",
                  "",
                  "",
                  "",
                  ""
                ],
                "type": "TALK_EXEC_NONE"
              },
              {
                "param": [
                  "",
                  "",
                  "",
                  "",
                  ""
                ],
                "type": "TALK_EXEC_NONE"
              },
              {
                "param": [
                  "",
                  "",
                  "",
                  "",
                  ""
                ],
                "type": "TALK_EXEC_NONE"
              }
            ],
            "forceNpcNotDestroy": false,
            "heroRuleId": 0,
            "ignoreDragonTalkRule": false,
            "isEnableNoBlackInter": false,
            "linkBehaviorGrpId": 0,
            "loadType": "TALK_NORMAL_QUEST",
            "lockGameTime": false,
            "lowPriority": false,
            "newTalkFinishTime": false,
            "onlyQuestNpc": false,
            "participantId": [],
            "prePerformCfg": "",
            "questIdleTalk": false,
            "randomTalkPos": 0,
            "randomTalkPriorityList": [],
            "removeDuplicatedRandomTalk": false,
            "stayFreeStyle": false,
            "talkMarkHideList": [],
            "talkMarkType": "TALK_MARK_NONE",
            "activeMode": "PLAY_MODE_ALL",
            "beginCond": [
              {
                "param": [
                  "2010404",
                  "2",
                  "",
                  "",
                  ""
                ],
                "type": "QUEST_COND_STATE_EQUAL"
              },
              {
                "param": [
                  "2010402",
                  "3",
                  "",
                  "",
                  ""
                ],
                "type": "QUEST_COND_STATE_EQUAL"
              },
              {
                "param": [
                  "",
                  "",
                  "",
                  "",
                  ""
                ],
                "type": "QUEST_COND_NONE"
              },
              {
                "param": [
                  "",
                  "",
                  "",
                  "",
                  ""
                ],
                "type": "QUEST_COND_NONE"
              },
              {
                "param": [
                  "",
                  "",
                  "",
                  "",
                  ""
                ],
                "type": "QUEST_COND_NONE"
              },
              {
                "param": [
                  "",
                  "",
                  "",
                  "",
                  ""
                ],
                "type": "QUEST_COND_NONE"
              },
              {
                "param": [
                  "",
                  "",
                  "",
                  "",
                  ""
                ],
                "type": "QUEST_COND_NONE"
              },
              {
                "param": [
                  "",
                  "",
                  "",
                  "",
                  ""
                ],
                "type": "QUEST_COND_NONE"
              },
              {
                "param": [
                  "",
                  "",
                  "",
                  "",
                  ""
                ],
                "type": "QUEST_COND_NONE"
              },
              {
                "param": [
                  "",
                  "",
                  "",
                  "",
                  ""
                ],
                "type": "QUEST_COND_NONE"
              }
            ],
            "beginCondComb": "LOGIC_AND",
            "beginWay": "TALK_BEGIN_MANUAL",
            "heroTalk": "TALK_HERO_MAIN",
            "id": 2010402,
            "initDialog": 201040201,
            "nextRandomTalks": [],
            "nextTalks": [],
            "npcId": [
              1596
            ],
            "performCfg": "",
            "priority": 3,
            "questId": 20104,
            "showRandomTalkCount": 0
          },
          "dialogs": [
            {
              "nodeId": 201040201,
              "roleType": "TALK_ROLE_NPC",
              "speakerId": 1596,
              "speakerName": "摩可",
              "textMapHash": 1184532098,
              "text": "怎么样？",
              "nextNodeIds": [
                201040202
              ]
            },
            {
              "nodeId": 201040202,
              "roleType": "TALK_ROLE_NPC",
              "speakerId": 1595,
              "speakerName": "海莉",
              "textMapHash": 857688106,
              "text": "打扫干净了吗？",
              "nextNodeIds": [
                201040203
              ]
            },
            {
              "nodeId": 201040203,
              "roleType": "TALK_ROLE_PLAYER",
              "speakerId": null,
              "speakerName": "旅行者",
              "textMapHash": 2365076042,
              "text": "已经打扫干净了。",
              "nextNodeIds": [
                201040204
              ]
            },
            {
              "nodeId": 201040204,
              "roleType": "TALK_ROLE_NPC",
              "speakerId": 1596,
              "speakerName": "摩可",
              "textMapHash": 529926402,
              "text": "太厉害了！",
              "nextNodeIds": [
                201040205
              ]
            },
            {
              "nodeId": 201040205,
              "roleType": "TALK_ROLE_NPC",
              "speakerId": 1595,
              "speakerName": "海莉",
              "textMapHash": 136051370,
              "text": "不愧是旅行者！",
              "nextNodeIds": [
                201040206
              ]
            },
            {
              "nodeId": 201040206,
              "roleType": "TALK_ROLE_NPC",
              "speakerId": 1596,
              "speakerName": "摩可",
              "textMapHash": 3681706714,
              "text": "这样就不用被女仆长骂了，谢谢你。",
              "nextNodeIds": [
                201040207
              ]
            },
            {
              "nodeId": 201040207,
              "roleType": "TALK_ROLE_NPC",
              "speakerId": 1595,
              "speakerName": "海莉",
              "textMapHash": 4250137114,
              "text": "这些请收下，就算是谢礼吧。",
              "nextNodeIds": [
                201040208
              ]
            },
            {
              "nodeId": 201040208,
              "roleType": "TALK_ROLE_NPC",
              "speakerId": 1596,
              "speakerName": "摩可",
              "textMapHash": 585258362,
              "text": "我们得赶紧打扫别的地方去了…再次谢谢你帮忙！",
              "nextNodeIds": []
            }
          ]
        },
        {
          "talkId": 2010405,
          "talkConfig": {
            "checkActionAfter": false,
            "crowdLOD0List": [],
            "decoratorID": 0,
            "disableTalkReview": false,
            "dontBlockDaily": false,
            "enableCameraDisplacement": false,
            "extraLoadMarkId": [],
            "finishExec": [
              {
                "param": [
                  "",
                  "",
                  "",
                  "",
                  ""
                ],
                "type": "TALK_EXEC_NONE"
              },
              {
                "param": [
                  "",
                  "",
                  "",
                  "",
                  ""
                ],
                "type": "TALK_EXEC_NONE"
              },
              {
                "param": [
                  "",
                  "",
                  "",
                  "",
                  ""
                ],
                "type": "TALK_EXEC_NONE"
              },
              {
                "param": [
                  "",
                  "",
                  "",
                  "",
                  ""
                ],
                "type": "TALK_EXEC_NONE"
              },
              {
                "param": [
                  "",
                  "",
                  "",
                  "",
                  ""
                ],
                "type": "TALK_EXEC_NONE"
              }
            ],
            "forceNpcNotDestroy": false,
            "heroRuleId": 0,
            "ignoreDragonTalkRule": false,
            "isEnableNoBlackInter": false,
            "linkBehaviorGrpId": 0,
            "loadType": "TALK_NORMAL_QUEST",
            "lockGameTime": false,
            "lowPriority": false,
            "newTalkFinishTime": false,
            "onlyQuestNpc": false,
            "participantId": [],
            "prePerformCfg": "",
            "questIdleTalk": false,
            "randomTalkPos": 0,
            "randomTalkPriorityList": [],
            "removeDuplicatedRandomTalk": false,
            "stayFreeStyle": false,
            "talkMarkHideList": [],
            "talkMarkType": "TALK_MARK_NONE",
            "activeMode": "PLAY_MODE_ALL",
            "beginCond": [
              {
                "param": [
                  "2010402",
                  "2",
                  "",
                  "",
                  ""
                ],
                "type": "QUEST_COND_STATE_EQUAL"
              },
              {
                "param": [
                  "",
                  "",
                  "",
                  "",
                  ""
                ],
                "type": "QUEST_COND_NONE"
              },
              {
                "param": [
                  "",
                  "",
                  "",
                  "",
                  ""
                ],
                "type": "QUEST_COND_NONE"
              },
              {
                "param": [
                  "",
                  "",
                  "",
                  "",
                  ""
                ],
                "type": "QUEST_COND_NONE"
              },
              {
                "param": [
                  "",
                  "",
                  "",
                  "",
                  ""
                ],
                "type": "QUEST_COND_NONE"
              },
              {
                "param": [
                  "",
                  "",
                  "",
                  "",
                  ""
                ],
                "type": "QUEST_COND_NONE"
              },
              {
                "param": [
                  "",
                  "",
                  "",
                  "",
                  ""
                ],
                "type": "QUEST_COND_NONE"
              },
              {
                "param": [
                  "",
                  "",
                  "",
                  "",
                  ""
                ],
                "type": "QUEST_COND_NONE"
              },
              {
                "param": [
                  "",
                  "",
                  "",
                  "",
                  ""
                ],
                "type": "QUEST_COND_NONE"
              },
              {
                "param": [
                  "",
                  "",
                  "",
                  "",
                  ""
                ],
                "type": "QUEST_COND_NONE"
              }
            ],
            "beginCondComb": "LOGIC_NONE",
            "beginWay": "TALK_BEGIN_MANUAL",
            "heroTalk": "TALK_HERO_MAIN",
            "id": 2010405,
            "initDialog": 201040501,
            "nextRandomTalks": [],
            "nextTalks": [],
            "npcId": [
              1596
            ],
            "performCfg": "",
            "priority": 0,
            "questId": 20104,
            "showRandomTalkCount": 0
          },
          "dialogs": [
            {
              "nodeId": 201040501,
              "roleType": "TALK_ROLE_NPC",
              "speakerId": 1596,
              "speakerName": "摩可",
              "textMapHash": 2794399586,
              "text": "呜…衣服全都弄脏了。",
              "nextNodeIds": [
                201040502
              ]
            },
            {
              "nodeId": 201040502,
              "roleType": "TALK_ROLE_NPC",
              "speakerId": 1595,
              "speakerName": "海莉",
              "textMapHash": 3487317410,
              "text": "而且落叶也没打扫干净。",
              "nextNodeIds": [
                201040503
              ]
            },
            {
              "nodeId": 201040503,
              "roleType": "TALK_ROLE_NPC",
              "speakerId": 1596,
              "speakerName": "摩可",
              "textMapHash": 2631885690,
              "text": "这可怎么办呐…",
              "nextNodeIds": []
            }
          ]
        },
        {
          "talkId": 2010406,
          "talkConfig": {
            "checkActionAfter": false,
            "crowdLOD0List": [],
            "decoratorID": 0,
            "disableTalkReview": false,
            "dontBlockDaily": false,
            "enableCameraDisplacement": false,
            "extraLoadMarkId": [],
            "finishExec": [
              {
                "param": [
                  "",
                  "",
                  "",
                  "",
                  ""
                ],
                "type": "TALK_EXEC_NONE"
              },
              {
                "param": [
                  "",
                  "",
                  "",
                  "",
                  ""
                ],
                "type": "TALK_EXEC_NONE"
              },
              {
                "param": [
                  "",
                  "",
                  "",
                  "",
                  ""
                ],
                "type": "TALK_EXEC_NONE"
              },
              {
                "param": [
                  "",
                  "",
                  "",
                  "",
                  ""
                ],
                "type": "TALK_EXEC_NONE"
              },
              {
                "param": [
                  "",
                  "",
                  "",
                  "",
                  ""
                ],
                "type": "TALK_EXEC_NONE"
              }
            ],
            "forceNpcNotDestroy": false,
            "heroRuleId": 0,
            "ignoreDragonTalkRule": false,
            "isEnableNoBlackInter": false,
            "linkBehaviorGrpId": 0,
            "loadType": "TALK_NORMAL_QUEST",
            "lockGameTime": false,
            "lowPriority": false,
            "newTalkFinishTime": false,
            "onlyQuestNpc": false,
            "participantId": [],
            "prePerformCfg": "",
            "questIdleTalk": false,
            "randomTalkPos": 0,
            "randomTalkPriorityList": [],
            "removeDuplicatedRandomTalk": false,
            "stayFreeStyle": false,
            "talkMarkHideList": [],
            "talkMarkType": "TALK_MARK_NONE",
            "activeMode": "PLAY_MODE_ALL",
            "beginCond": [
              {
                "param": [
                  "2010402",
                  "2",
                  "",
                  "",
                  ""
                ],
                "type": "QUEST_COND_STATE_EQUAL"
              },
              {
                "param": [
                  "",
                  "",
                  "",
                  "",
                  ""
                ],
                "type": "QUEST_COND_NONE"
              },
              {
                "param": [
                  "",
                  "",
                  "",
                  "",
                  ""
                ],
                "type": "QUEST_COND_NONE"
              },
              {
                "param": [
                  "",
                  "",
                  "",
                  "",
                  ""
                ],
                "type": "QUEST_COND_NONE"
              },
              {
                "param": [
                  "",
                  "",
                  "",
                  "",
                  ""
                ],
                "type": "QUEST_COND_NONE"
              },
              {
                "param": [
                  "",
                  "",
                  "",
                  "",
                  ""
                ],
                "type": "QUEST_COND_NONE"
              },
              {
                "param": [
                  "",
                  "",
                  "",
                  "",
                  ""
                ],
                "type": "QUEST_COND_NONE"
              },
              {
                "param": [
                  "",
                  "",
                  "",
                  "",
                  ""
                ],
                "type": "QUEST_COND_NONE"
              },
              {
                "param": [
                  "",
                  "",
                  "",
                  "",
                  ""
                ],
                "type": "QUEST_COND_NONE"
              },
              {
                "param": [
                  "",
                  "",
                  "",
                  "",
                  ""
                ],
                "type": "QUEST_COND_NONE"
              }
            ],
            "beginCondComb": "LOGIC_NONE",
            "beginWay": "TALK_BEGIN_MANUAL",
            "heroTalk": "TALK_HERO_MAIN",
            "id": 2010406,
            "initDialog": 201040601,
            "nextRandomTalks": [],
            "nextTalks": [],
            "npcId": [
              1595
            ],
            "performCfg": "",
            "priority": 0,
            "questId": 20104,
            "showRandomTalkCount": 0
          },
          "dialogs": [
            {
              "nodeId": 201040601,
              "roleType": "TALK_ROLE_NPC",
              "speakerId": 1596,
              "speakerName": "摩可",
              "textMapHash": 2141243146,
              "text": "呜…衣服全都弄脏了。",
              "nextNodeIds": [
                201040602
              ]
            },
            {
              "nodeId": 201040602,
              "roleType": "TALK_ROLE_NPC",
              "speakerId": 1595,
              "speakerName": "海莉",
              "textMapHash": 2710549826,
              "text": "而且落叶也没打扫干净。",
              "nextNodeIds": [
                201040603
              ]
            },
            {
              "nodeId": 201040603,
              "roleType": "TALK_ROLE_NPC",
              "speakerId": 1596,
              "speakerName": "摩可",
              "textMapHash": 2069096162,
              "text": "这可怎么办呐…",
              "nextNodeIds": []
            }
          ]
        }
      ],
      "conditions": {
        "finishCond": [
          {
            "BFGALAINLMD": 5,
            "LNHLPKELCAL": [
              2010402,
              0
            ],
            "PAINLIBBLDK": "QUEST_CONTENT_LUA_NOTIFY",
            "PPFLKMOMKAI": "1330029061"
          }
        ],
        "triggerCond": [
          {
            "BFGALAINLMD": 1,
            "LNHLPKELCAL": [
              0,
              0
            ],
            "PAINLIBBLDK": "QUEST_CONTENT_LUA_NOTIFY",
            "PPFLKMOMKAI": "1330029051"
          }
        ],
        "execActions": [
          {
            "LNHLPKELCAL": [
              "2010304",
              "1"
            ],
            "PAINLIBBLDK": "QUEST_EXEC_ADD_QUEST_PROGRESS"
          }
        ],
        "guide": {
          "BEALNDJFMMC": "QUEST_GUIDE_IN_SCENE_STYLE_NONE",
          "BJKFMDGPIBN": "QUEST_GUIDE_INDICATOR_STYLE_NONE",
          "CCLPMCLNLBJ": "NONE",
          "CJHEDKCIHPA": 0,
          "EMAIGPLHEJH": "QUEST_GUIDE_LAYER_SCENE",
          "GGJOHCAJAPP": 0,
          "HFNCMGLBNGO": "",
          "IDLNFDCEJLG": "QUEST_GUIDE_AREA_STYLE_DEFAULT",
          "KCFINIEBBBG": 0,
          "KEDGDANLBHP": "",
          "KNMAMMFJAOB": "QUEST_GUIDE_STYLE_POINT",
          "LNHLPKELCAL": [
            "Q20104Target",
            "30"
          ],
          "NOCCOBOFKHP": 3,
          "OFEBJNGBEPL": "QUEST_GUIDE_AUTO_NONE",
          "PAINLIBBLDK": "QUEST_GUIDE_LOCATION"
        }
      }
    },
    {
      "subQuestId": 2010403,
      "order": 3,
      "stepDescription": "(test)判断烧掉草垛$HIDDEN",
      "stepDescTextMapHash": 1498063756,
      "finishConds": [
        {
          "BFGALAINLMD": 1,
          "LNHLPKELCAL": [
            2010403,
            0
          ],
          "PAINLIBBLDK": "QUEST_CONTENT_LUA_NOTIFY",
          "PPFLKMOMKAI": "1330029051"
        }
      ],
      "guide": {
        "BEALNDJFMMC": "QUEST_GUIDE_IN_SCENE_STYLE_NONE",
        "BJKFMDGPIBN": "QUEST_GUIDE_INDICATOR_STYLE_NONE",
        "CCLPMCLNLBJ": "NONE",
        "CJHEDKCIHPA": 0,
        "EMAIGPLHEJH": "QUEST_GUIDE_LAYER_NONE",
        "GGJOHCAJAPP": 0,
        "HFNCMGLBNGO": "",
        "IDLNFDCEJLG": "QUEST_GUIDE_AREA_STYLE_DEFAULT",
        "KCFINIEBBBG": 0,
        "KEDGDANLBHP": "",
        "KNMAMMFJAOB": "QUEST_GUIDE_STYLE_NONE",
        "LNHLPKELCAL": [],
        "NOCCOBOFKHP": 0,
        "OFEBJNGBEPL": "QUEST_GUIDE_AUTO_NONE",
        "PAINLIBBLDK": "QUEST_GUIDE_NONE"
      },
      "isHidden": false,
      "talkIds": [
        2010403
      ],
      "talks": [
        {
          "talkId": 2010403,
          "talkConfig": {
            "checkActionAfter": false,
            "crowdLOD0List": [],
            "decoratorID": 0,
            "disableTalkReview": false,
            "dontBlockDaily": false,
            "enableCameraDisplacement": false,
            "extraLoadMarkId": [],
            "finishExec": [
              {
                "param": [
                  "",
                  "",
                  "",
                  "",
                  ""
                ],
                "type": "TALK_EXEC_NONE"
              },
              {
                "param": [
                  "",
                  "",
                  "",
                  "",
                  ""
                ],
                "type": "TALK_EXEC_NONE"
              },
              {
                "param": [
                  "",
                  "",
                  "",
                  "",
                  ""
                ],
                "type": "TALK_EXEC_NONE"
              },
              {
                "param": [
                  "",
                  "",
                  "",
                  "",
                  ""
                ],
                "type": "TALK_EXEC_NONE"
              },
              {
                "param": [
                  "",
                  "",
                  "",
                  "",
                  ""
                ],
                "type": "TALK_EXEC_NONE"
              }
            ],
            "forceNpcNotDestroy": false,
            "heroRuleId": 0,
            "ignoreDragonTalkRule": false,
            "isEnableNoBlackInter": false,
            "linkBehaviorGrpId": 0,
            "loadType": "TALK_NORMAL_QUEST",
            "lockGameTime": false,
            "lowPriority": false,
            "newTalkFinishTime": false,
            "onlyQuestNpc": false,
            "participantId": [],
            "prePerformCfg": "",
            "questIdleTalk": false,
            "randomTalkPos": 0,
            "randomTalkPriorityList": [],
            "removeDuplicatedRandomTalk": false,
            "stayFreeStyle": false,
            "talkMarkHideList": [],
            "talkMarkType": "TALK_MARK_NONE",
            "activeMode": "PLAY_MODE_ALL",
            "beginCond": [
              {
                "param": [
                  "2010404",
                  "2",
                  "",
                  "",
                  ""
                ],
                "type": "QUEST_COND_STATE_EQUAL"
              },
              {
                "param": [
                  "2010403",
                  "3",
                  "",
                  "",
                  ""
                ],
                "type": "QUEST_COND_STATE_EQUAL"
              },
              {
                "param": [
                  "",
                  "",
                  "",
                  "",
                  ""
                ],
                "type": "QUEST_COND_NONE"
              },
              {
                "param": [
                  "",
                  "",
                  "",
                  "",
                  ""
                ],
                "type": "QUEST_COND_NONE"
              },
              {
                "param": [
                  "",
                  "",
                  "",
                  "",
                  ""
                ],
                "type": "QUEST_COND_NONE"
              },
              {
                "param": [
                  "",
                  "",
                  "",
                  "",
                  ""
                ],
                "type": "QUEST_COND_NONE"
              },
              {
                "param": [
                  "",
                  "",
                  "",
                  "",
                  ""
                ],
                "type": "QUEST_COND_NONE"
              },
              {
                "param": [
                  "",
                  "",
                  "",
                  "",
                  ""
                ],
                "type": "QUEST_COND_NONE"
              },
              {
                "param": [
                  "",
                  "",
                  "",
                  "",
                  ""
                ],
                "type": "QUEST_COND_NONE"
              },
              {
                "param": [
                  "",
                  "",
                  "",
                  "",
                  ""
                ],
                "type": "QUEST_COND_NONE"
              }
            ],
            "beginCondComb": "LOGIC_AND",
            "beginWay": "TALK_BEGIN_MANUAL",
            "heroTalk": "TALK_HERO_MAIN",
            "id": 2010403,
            "initDialog": 201040301,
            "nextRandomTalks": [],
            "nextTalks": [],
            "npcId": [
              1596
            ],
            "performCfg": "",
            "priority": 5,
            "questId": 20104,
            "showRandomTalkCount": 0
          },
          "dialogs": [
            {
              "nodeId": 201040301,
              "roleType": "TALK_ROLE_NPC",
              "speakerId": 1596,
              "speakerName": "摩可",
              "textMapHash": 372936002,
              "text": "你，你做什么呀，怎么把整个草垛都烧掉了！",
              "nextNodeIds": [
                201040302
              ]
            },
            {
              "nodeId": 201040302,
              "roleType": "TALK_ROLE_NPC",
              "speakerId": 1595,
              "speakerName": "海莉",
              "textMapHash": 870990098,
              "text": "这回不是被骂就能了事了，一定会被开除…",
              "nextNodeIds": [
                201040303
              ]
            },
            {
              "nodeId": 201040303,
              "roleType": "TALK_ROLE_PLAYER",
              "speakerId": null,
              "speakerName": "旅行者",
              "textMapHash": 2291511066,
              "text": "一不小心就…",
              "nextNodeIds": [
                201040304
              ]
            },
            {
              "nodeId": 201040304,
              "roleType": "TALK_ROLE_NPC",
              "speakerId": 1596,
              "speakerName": "摩可",
              "textMapHash": 3770046130,
              "text": "早知道，我们还不如慢慢地一点点把落叶挑出来了…",
              "nextNodeIds": [
                201040305
              ]
            },
            {
              "nodeId": 201040305,
              "roleType": "TALK_ROLE_NPC",
              "speakerId": 1595,
              "speakerName": "海莉",
              "textMapHash": 3414666394,
              "text": "完了…这下子全完了…",
              "nextNodeIds": [
                201040306
              ]
            },
            {
              "nodeId": 201040306,
              "roleType": "TALK_ROLE_PLAYER",
              "speakerId": null,
              "speakerName": "旅行者",
              "textMapHash": 2980779930,
              "text": "那个…",
              "nextNodeIds": [
                201040307
              ]
            },
            {
              "nodeId": 201040307,
              "roleType": "TALK_ROLE_NPC",
              "speakerId": 1596,
              "speakerName": "摩可",
              "textMapHash": 153406474,
              "text": "旅行者，请你快点离开吧，这件事是我们的责任…",
              "nextNodeIds": [
                201040308
              ]
            },
            {
              "nodeId": 201040308,
              "roleType": "TALK_ROLE_NPC",
              "speakerId": 1595,
              "speakerName": "海莉",
              "textMapHash": 612304482,
              "text": "我们不该让不懂得打扫方法的人来帮忙，是我们错了…",
              "nextNodeIds": [
                201040309
              ]
            },
            {
              "nodeId": 201040309,
              "roleType": "TALK_ROLE_NPC",
              "speakerId": 1596,
              "speakerName": "摩可",
              "textMapHash": 3259814330,
              "text": "女仆长会怎么处置我们呢…",
              "nextNodeIds": [
                201040310
              ]
            },
            {
              "nodeId": 201040310,
              "roleType": "TALK_ROLE_NPC",
              "speakerId": 1595,
              "speakerName": "海莉",
              "textMapHash": 2754242626,
              "text": "这下子，全都完了…",
              "nextNodeIds": []
            }
          ]
        }
      ],
      "conditions": {
        "finishCond": [
          {
            "BFGALAINLMD": 1,
            "LNHLPKELCAL": [
              2010403,
              0
            ],
            "PAINLIBBLDK": "QUEST_CONTENT_LUA_NOTIFY",
            "PPFLKMOMKAI": "1330029051"
          }
        ],
        "triggerCond": [
          {
            "BFGALAINLMD": 1,
            "LNHLPKELCAL": [
              2010403,
              0
            ],
            "PAINLIBBLDK": "QUEST_CONTENT_ADD_QUEST_PROGRESS",
            "PPFLKMOMKAI": ""
          }
        ],
        "execActions": [],
        "guide": {
          "BEALNDJFMMC": "QUEST_GUIDE_IN_SCENE_STYLE_NONE",
          "BJKFMDGPIBN": "QUEST_GUIDE_INDICATOR_STYLE_NONE",
          "CCLPMCLNLBJ": "NONE",
          "CJHEDKCIHPA": 0,
          "EMAIGPLHEJH": "QUEST_GUIDE_LAYER_NONE",
          "GGJOHCAJAPP": 0,
          "HFNCMGLBNGO": "",
          "IDLNFDCEJLG": "QUEST_GUIDE_AREA_STYLE_DEFAULT",
          "KCFINIEBBBG": 0,
          "KEDGDANLBHP": "",
          "KNMAMMFJAOB": "QUEST_GUIDE_STYLE_NONE",
          "LNHLPKELCAL": [],
          "NOCCOBOFKHP": 0,
          "OFEBJNGBEPL": "QUEST_GUIDE_AUTO_NONE",
          "PAINLIBBLDK": "QUEST_GUIDE_NONE"
        }
      }
    },
    {
      "subQuestId": 2010404,
      "order": 4,
      "stepDescription": "与摩可和海莉对话",
      "stepDescTextMapHash": 3213579636,
      "finishConds": [
        {
          "BFGALAINLMD": 0,
          "LNHLPKELCAL": [
            2010402,
            0
          ],
          "PAINLIBBLDK": "QUEST_CONTENT_COMPLETE_TALK",
          "PPFLKMOMKAI": ""
        },
        {
          "BFGALAINLMD": 0,
          "LNHLPKELCAL": [
            2010403,
            0
          ],
          "PAINLIBBLDK": "QUEST_CONTENT_COMPLETE_TALK",
          "PPFLKMOMKAI": ""
        }
      ],
      "guide": {
        "BEALNDJFMMC": "QUEST_GUIDE_IN_SCENE_STYLE_NONE",
        "BJKFMDGPIBN": "QUEST_GUIDE_INDICATOR_STYLE_NONE",
        "CCLPMCLNLBJ": "NONE",
        "CJHEDKCIHPA": 0,
        "EMAIGPLHEJH": "QUEST_GUIDE_LAYER_SCENE",
        "GGJOHCAJAPP": 0,
        "HFNCMGLBNGO": "",
        "IDLNFDCEJLG": "QUEST_GUIDE_AREA_STYLE_DEFAULT",
        "KCFINIEBBBG": 0,
        "KEDGDANLBHP": "",
        "KNMAMMFJAOB": "QUEST_GUIDE_STYLE_FINISH",
        "LNHLPKELCAL": [
          "1596"
        ],
        "NOCCOBOFKHP": 3,
        "OFEBJNGBEPL": "QUEST_GUIDE_AUTO_NONE",
        "PAINLIBBLDK": "QUEST_GUIDE_NPC"
      },
      "isHidden": false,
      "talkIds": [
        2010402,
        2010403
      ],
      "talks": [
        {
          "talkId": 2010402,
          "talkConfig": {
            "checkActionAfter": false,
            "crowdLOD0List": [],
            "decoratorID": 0,
            "disableTalkReview": false,
            "dontBlockDaily": false,
            "enableCameraDisplacement": false,
            "extraLoadMarkId": [],
            "finishExec": [
              {
                "param": [
                  "",
                  "",
                  "",
                  "",
                  ""
                ],
                "type": "TALK_EXEC_NONE"
              },
              {
                "param": [
                  "",
                  "",
                  "",
                  "",
                  ""
                ],
                "type": "TALK_EXEC_NONE"
              },
              {
                "param": [
                  "",
                  "",
                  "",
                  "",
                  ""
                ],
                "type": "TALK_EXEC_NONE"
              },
              {
                "param": [
                  "",
                  "",
                  "",
                  "",
                  ""
                ],
                "type": "TALK_EXEC_NONE"
              },
              {
                "param": [
                  "",
                  "",
                  "",
                  "",
                  ""
                ],
                "type": "TALK_EXEC_NONE"
              }
            ],
            "forceNpcNotDestroy": false,
            "heroRuleId": 0,
            "ignoreDragonTalkRule": false,
            "isEnableNoBlackInter": false,
            "linkBehaviorGrpId": 0,
            "loadType": "TALK_NORMAL_QUEST",
            "lockGameTime": false,
            "lowPriority": false,
            "newTalkFinishTime": false,
            "onlyQuestNpc": false,
            "participantId": [],
            "prePerformCfg": "",
            "questIdleTalk": false,
            "randomTalkPos": 0,
            "randomTalkPriorityList": [],
            "removeDuplicatedRandomTalk": false,
            "stayFreeStyle": false,
            "talkMarkHideList": [],
            "talkMarkType": "TALK_MARK_NONE",
            "activeMode": "PLAY_MODE_ALL",
            "beginCond": [
              {
                "param": [
                  "2010404",
                  "2",
                  "",
                  "",
                  ""
                ],
                "type": "QUEST_COND_STATE_EQUAL"
              },
              {
                "param": [
                  "2010402",
                  "3",
                  "",
                  "",
                  ""
                ],
                "type": "QUEST_COND_STATE_EQUAL"
              },
              {
                "param": [
                  "",
                  "",
                  "",
                  "",
                  ""
                ],
                "type": "QUEST_COND_NONE"
              },
              {
                "param": [
                  "",
                  "",
                  "",
                  "",
                  ""
                ],
                "type": "QUEST_COND_NONE"
              },
              {
                "param": [
                  "",
                  "",
                  "",
                  "",
                  ""
                ],
                "type": "QUEST_COND_NONE"
              },
              {
                "param": [
                  "",
                  "",
                  "",
                  "",
                  ""
                ],
                "type": "QUEST_COND_NONE"
              },
              {
                "param": [
                  "",
                  "",
                  "",
                  "",
                  ""
                ],
                "type": "QUEST_COND_NONE"
              },
              {
                "param": [
                  "",
                  "",
                  "",
                  "",
                  ""
                ],
                "type": "QUEST_COND_NONE"
              },
              {
                "param": [
                  "",
                  "",
                  "",
                  "",
                  ""
                ],
                "type": "QUEST_COND_NONE"
              },
              {
                "param": [
                  "",
                  "",
                  "",
                  "",
                  ""
                ],
                "type": "QUEST_COND_NONE"
              }
            ],
            "beginCondComb": "LOGIC_AND",
            "beginWay": "TALK_BEGIN_MANUAL",
            "heroTalk": "TALK_HERO_MAIN",
            "id": 2010402,
            "initDialog": 201040201,
            "nextRandomTalks": [],
            "nextTalks": [],
            "npcId": [
              1596
            ],
            "performCfg": "",
            "priority": 3,
            "questId": 20104,
            "showRandomTalkCount": 0
          },
          "dialogs": [
            {
              "nodeId": 201040201,
              "roleType": "TALK_ROLE_NPC",
              "speakerId": 1596,
              "speakerName": "摩可",
              "textMapHash": 1184532098,
              "text": "怎么样？",
              "nextNodeIds": [
                201040202
              ]
            },
            {
              "nodeId": 201040202,
              "roleType": "TALK_ROLE_NPC",
              "speakerId": 1595,
              "speakerName": "海莉",
              "textMapHash": 857688106,
              "text": "打扫干净了吗？",
              "nextNodeIds": [
                201040203
              ]
            },
            {
              "nodeId": 201040203,
              "roleType": "TALK_ROLE_PLAYER",
              "speakerId": null,
              "speakerName": "旅行者",
              "textMapHash": 2365076042,
              "text": "已经打扫干净了。",
              "nextNodeIds": [
                201040204
              ]
            },
            {
              "nodeId": 201040204,
              "roleType": "TALK_ROLE_NPC",
              "speakerId": 1596,
              "speakerName": "摩可",
              "textMapHash": 529926402,
              "text": "太厉害了！",
              "nextNodeIds": [
                201040205
              ]
            },
            {
              "nodeId": 201040205,
              "roleType": "TALK_ROLE_NPC",
              "speakerId": 1595,
              "speakerName": "海莉",
              "textMapHash": 136051370,
              "text": "不愧是旅行者！",
              "nextNodeIds": [
                201040206
              ]
            },
            {
              "nodeId": 201040206,
              "roleType": "TALK_ROLE_NPC",
              "speakerId": 1596,
              "speakerName": "摩可",
              "textMapHash": 3681706714,
              "text": "这样就不用被女仆长骂了，谢谢你。",
              "nextNodeIds": [
                201040207
              ]
            },
            {
              "nodeId": 201040207,
              "roleType": "TALK_ROLE_NPC",
              "speakerId": 1595,
              "speakerName": "海莉",
              "textMapHash": 4250137114,
              "text": "这些请收下，就算是谢礼吧。",
              "nextNodeIds": [
                201040208
              ]
            },
            {
              "nodeId": 201040208,
              "roleType": "TALK_ROLE_NPC",
              "speakerId": 1596,
              "speakerName": "摩可",
              "textMapHash": 585258362,
              "text": "我们得赶紧打扫别的地方去了…再次谢谢你帮忙！",
              "nextNodeIds": []
            }
          ]
        },
        {
          "talkId": 2010403,
          "talkConfig": {
            "checkActionAfter": false,
            "crowdLOD0List": [],
            "decoratorID": 0,
            "disableTalkReview": false,
            "dontBlockDaily": false,
            "enableCameraDisplacement": false,
            "extraLoadMarkId": [],
            "finishExec": [
              {
                "param": [
                  "",
                  "",
                  "",
                  "",
                  ""
                ],
                "type": "TALK_EXEC_NONE"
              },
              {
                "param": [
                  "",
                  "",
                  "",
                  "",
                  ""
                ],
                "type": "TALK_EXEC_NONE"
              },
              {
                "param": [
                  "",
                  "",
                  "",
                  "",
                  ""
                ],
                "type": "TALK_EXEC_NONE"
              },
              {
                "param": [
                  "",
                  "",
                  "",
                  "",
                  ""
                ],
                "type": "TALK_EXEC_NONE"
              },
              {
                "param": [
                  "",
                  "",
                  "",
                  "",
                  ""
                ],
                "type": "TALK_EXEC_NONE"
              }
            ],
            "forceNpcNotDestroy": false,
            "heroRuleId": 0,
            "ignoreDragonTalkRule": false,
            "isEnableNoBlackInter": false,
            "linkBehaviorGrpId": 0,
            "loadType": "TALK_NORMAL_QUEST",
            "lockGameTime": false,
            "lowPriority": false,
            "newTalkFinishTime": false,
            "onlyQuestNpc": false,
            "participantId": [],
            "prePerformCfg": "",
            "questIdleTalk": false,
            "randomTalkPos": 0,
            "randomTalkPriorityList": [],
            "removeDuplicatedRandomTalk": false,
            "stayFreeStyle": false,
            "talkMarkHideList": [],
            "talkMarkType": "TALK_MARK_NONE",
            "activeMode": "PLAY_MODE_ALL",
            "beginCond": [
              {
                "param": [
                  "2010404",
                  "2",
                  "",
                  "",
                  ""
                ],
                "type": "QUEST_COND_STATE_EQUAL"
              },
              {
                "param": [
                  "2010403",
                  "3",
                  "",
                  "",
                  ""
                ],
                "type": "QUEST_COND_STATE_EQUAL"
              },
              {
                "param": [
                  "",
                  "",
                  "",
                  "",
                  ""
                ],
                "type": "QUEST_COND_NONE"
              },
              {
                "param": [
                  "",
                  "",
                  "",
                  "",
                  ""
                ],
                "type": "QUEST_COND_NONE"
              },
              {
                "param": [
                  "",
                  "",
                  "",
                  "",
                  ""
                ],
                "type": "QUEST_COND_NONE"
              },
              {
                "param": [
                  "",
                  "",
                  "",
                  "",
                  ""
                ],
                "type": "QUEST_COND_NONE"
              },
              {
                "param": [
                  "",
                  "",
                  "",
                  "",
                  ""
                ],
                "type": "QUEST_COND_NONE"
              },
              {
                "param": [
                  "",
                  "",
                  "",
                  "",
                  ""
                ],
                "type": "QUEST_COND_NONE"
              },
              {
                "param": [
                  "",
                  "",
                  "",
                  "",
                  ""
                ],
                "type": "QUEST_COND_NONE"
              },
              {
                "param": [
                  "",
                  "",
                  "",
                  "",
                  ""
                ],
                "type": "QUEST_COND_NONE"
              }
            ],
            "beginCondComb": "LOGIC_AND",
            "beginWay": "TALK_BEGIN_MANUAL",
            "heroTalk": "TALK_HERO_MAIN",
            "id": 2010403,
            "initDialog": 201040301,
            "nextRandomTalks": [],
            "nextTalks": [],
            "npcId": [
              1596
            ],
            "performCfg": "",
            "priority": 5,
            "questId": 20104,
            "showRandomTalkCount": 0
          },
          "dialogs": [
            {
              "nodeId": 201040301,
              "roleType": "TALK_ROLE_NPC",
              "speakerId": 1596,
              "speakerName": "摩可",
              "textMapHash": 372936002,
              "text": "你，你做什么呀，怎么把整个草垛都烧掉了！",
              "nextNodeIds": [
                201040302
              ]
            },
            {
              "nodeId": 201040302,
              "roleType": "TALK_ROLE_NPC",
              "speakerId": 1595,
              "speakerName": "海莉",
              "textMapHash": 870990098,
              "text": "这回不是被骂就能了事了，一定会被开除…",
              "nextNodeIds": [
                201040303
              ]
            },
            {
              "nodeId": 201040303,
              "roleType": "TALK_ROLE_PLAYER",
              "speakerId": null,
              "speakerName": "旅行者",
              "textMapHash": 2291511066,
              "text": "一不小心就…",
              "nextNodeIds": [
                201040304
              ]
            },
            {
              "nodeId": 201040304,
              "roleType": "TALK_ROLE_NPC",
              "speakerId": 1596,
              "speakerName": "摩可",
              "textMapHash": 3770046130,
              "text": "早知道，我们还不如慢慢地一点点把落叶挑出来了…",
              "nextNodeIds": [
                201040305
              ]
            },
            {
              "nodeId": 201040305,
              "roleType": "TALK_ROLE_NPC",
              "speakerId": 1595,
              "speakerName": "海莉",
              "textMapHash": 3414666394,
              "text": "完了…这下子全完了…",
              "nextNodeIds": [
                201040306
              ]
            },
            {
              "nodeId": 201040306,
              "roleType": "TALK_ROLE_PLAYER",
              "speakerId": null,
              "speakerName": "旅行者",
              "textMapHash": 2980779930,
              "text": "那个…",
              "nextNodeIds": [
                201040307
              ]
            },
            {
              "nodeId": 201040307,
              "roleType": "TALK_ROLE_NPC",
              "speakerId": 1596,
              "speakerName": "摩可",
              "textMapHash": 153406474,
              "text": "旅行者，请你快点离开吧，这件事是我们的责任…",
              "nextNodeIds": [
                201040308
              ]
            },
            {
              "nodeId": 201040308,
              "roleType": "TALK_ROLE_NPC",
              "speakerId": 1595,
              "speakerName": "海莉",
              "textMapHash": 612304482,
              "text": "我们不该让不懂得打扫方法的人来帮忙，是我们错了…",
              "nextNodeIds": [
                201040309
              ]
            },
            {
              "nodeId": 201040309,
              "roleType": "TALK_ROLE_NPC",
              "speakerId": 1596,
              "speakerName": "摩可",
              "textMapHash": 3259814330,
              "text": "女仆长会怎么处置我们呢…",
              "nextNodeIds": [
                201040310
              ]
            },
            {
              "nodeId": 201040310,
              "roleType": "TALK_ROLE_NPC",
              "speakerId": 1595,
              "speakerName": "海莉",
              "textMapHash": 2754242626,
              "text": "这下子，全都完了…",
              "nextNodeIds": []
            }
          ]
        }
      ],
      "conditions": {
        "finishCond": [
          {
            "BFGALAINLMD": 0,
            "LNHLPKELCAL": [
              2010402,
              0
            ],
            "PAINLIBBLDK": "QUEST_CONTENT_COMPLETE_TALK",
            "PPFLKMOMKAI": ""
          },
          {
            "BFGALAINLMD": 0,
            "LNHLPKELCAL": [
              2010403,
              0
            ],
            "PAINLIBBLDK": "QUEST_CONTENT_COMPLETE_TALK",
            "PPFLKMOMKAI": ""
          }
        ],
        "triggerCond": [],
        "execActions": [
          {
            "LNHLPKELCAL": [
              "24200"
            ],
            "PAINLIBBLDK": "QUEST_EXEC_NOTIFY_DAILY_TASK"
          }
        ],
        "guide": {
          "BEALNDJFMMC": "QUEST_GUIDE_IN_SCENE_STYLE_NONE",
          "BJKFMDGPIBN": "QUEST_GUIDE_INDICATOR_STYLE_NONE",
          "CCLPMCLNLBJ": "NONE",
          "CJHEDKCIHPA": 0,
          "EMAIGPLHEJH": "QUEST_GUIDE_LAYER_SCENE",
          "GGJOHCAJAPP": 0,
          "HFNCMGLBNGO": "",
          "IDLNFDCEJLG": "QUEST_GUIDE_AREA_STYLE_DEFAULT",
          "KCFINIEBBBG": 0,
          "KEDGDANLBHP": "",
          "KNMAMMFJAOB": "QUEST_GUIDE_STYLE_FINISH",
          "LNHLPKELCAL": [
            "1596"
          ],
          "NOCCOBOFKHP": 3,
          "OFEBJNGBEPL": "QUEST_GUIDE_AUTO_NONE",
          "PAINLIBBLDK": "QUEST_GUIDE_NPC"
        }
      }
    },
    {
      "subQuestId": 2010405,
      "order": 5,
      "stepDescription": "与摩可和海莉对话",
      "stepDescTextMapHash": 2312736620,
      "finishConds": [
        {
          "BFGALAINLMD": 0,
          "LNHLPKELCAL": [
            2010403,
            0
          ],
          "PAINLIBBLDK": "QUEST_CONTENT_COMPLETE_TALK",
          "PPFLKMOMKAI": ""
        }
      ],
      "guide": {
        "BEALNDJFMMC": "QUEST_GUIDE_IN_SCENE_STYLE_NONE",
        "BJKFMDGPIBN": "QUEST_GUIDE_INDICATOR_STYLE_NONE",
        "CCLPMCLNLBJ": "NONE",
        "CJHEDKCIHPA": 0,
        "EMAIGPLHEJH": "QUEST_GUIDE_LAYER_SCENE",
        "GGJOHCAJAPP": 0,
        "HFNCMGLBNGO": "",
        "IDLNFDCEJLG": "QUEST_GUIDE_AREA_STYLE_DEFAULT",
        "KCFINIEBBBG": 0,
        "KEDGDANLBHP": "",
        "KNMAMMFJAOB": "QUEST_GUIDE_STYLE_FINISH",
        "LNHLPKELCAL": [
          "1596"
        ],
        "NOCCOBOFKHP": 3,
        "OFEBJNGBEPL": "QUEST_GUIDE_AUTO_NONE",
        "PAINLIBBLDK": "QUEST_GUIDE_NPC"
      },
      "isHidden": false,
      "talkIds": [],
      "talks": [],
      "conditions": {
        "finishCond": [
          {
            "BFGALAINLMD": 0,
            "LNHLPKELCAL": [
              2010403,
              0
            ],
            "PAINLIBBLDK": "QUEST_CONTENT_COMPLETE_TALK",
            "PPFLKMOMKAI": ""
          }
        ],
        "triggerCond": [],
        "execActions": [
          {
            "LNHLPKELCAL": [
              "24200"
            ],
            "PAINLIBBLDK": "QUEST_EXEC_NOTIFY_DAILY_TASK"
          }
        ],
        "guide": {
          "BEALNDJFMMC": "QUEST_GUIDE_IN_SCENE_STYLE_NONE",
          "BJKFMDGPIBN": "QUEST_GUIDE_INDICATOR_STYLE_NONE",
          "CCLPMCLNLBJ": "NONE",
          "CJHEDKCIHPA": 0,
          "EMAIGPLHEJH": "QUEST_GUIDE_LAYER_SCENE",
          "GGJOHCAJAPP": 0,
          "HFNCMGLBNGO": "",
          "IDLNFDCEJLG": "QUEST_GUIDE_AREA_STYLE_DEFAULT",
          "KCFINIEBBBG": 0,
          "KEDGDANLBHP": "",
          "KNMAMMFJAOB": "QUEST_GUIDE_STYLE_FINISH",
          "LNHLPKELCAL": [
            "1596"
          ],
          "NOCCOBOFKHP": 3,
          "OFEBJNGBEPL": "QUEST_GUIDE_AUTO_NONE",
          "PAINLIBBLDK": "QUEST_GUIDE_NPC"
        }
      }
    }
  ],
  "unmappedTalks": [],
  "questNarration": [],
  "talkIds": [
    2010401,
    2010402,
    2010403,
    2010405,
    2010406
  ],
  "speakerCounts": [
    {
      "roleType": "TALK_ROLE_NPC",
      "speakerId": 1596,
      "speakerName": "摩可",
      "count": 17
    },
    {
      "roleType": "TALK_ROLE_NPC",
      "speakerId": 1595,
      "speakerName": "海莉",
      "count": 15
    },
    {
      "roleType": "TALK_ROLE_PLAYER",
      "speakerId": null,
      "speakerName": "旅行者",
      "count": 6
    }
  ],
  "raw": {
    "ANDJNFLIDIJ": "PLAY_MODE_ALL",
    "BEGCMMJKCFC": [],
    "BHCBFLFOGJN": 0,
    "BPEIDGPCLGA": true,
    "CBBBCAKOFGO": 3333074206,
    "CHECNJEMEFE": {},
    "CJPLOBIFHLG": "MAINQUEST_TAG_NONE",
    "CMDGLJAOFOJ": [],
    "EPJHBBICPCA": false,
    "FBEFCEJCBIK": {},
    "FFOAGHNMJKJ": 0,
    "FNFALGGACGA": "",
    "FOKHPBAGMPB": "",
    "GBFMDJLKJBF": [],
    "GMENNHMBBOH": [],
    "HCJHEADFCAO": 0,
    "IBEGAHMEABP": [
      {
        "<DLGBBMLABOA>k__BackingField": 0,
        "ABDCADBLCFC": 0,
        "AIMIPKGBAHC": "",
        "ANDJNFLIDIJ": "PLAY_MODE_ALL",
        "AOLKCANJCMJ": 0,
        "BKDENCDKDEE": "",
        "BPIIFMJLJAJ": [],
        "DAMGEPEMGNO": false,
        "DBACCKDPONG": [],
        "DIAFFIANKPH": false,
        "DKOMBMCJMMN": false,
        "EFBOKHEHKJM": [],
        "EIDINNIHMHD": false,
        "EKANPNMEFMG": [],
        "ENDBMMDPPAH": [],
        "FALLCBHGKON": "LOGIC_NONE",
        "GEPGLHFDBNF": [],
        "GLJMLHNKKKO": "TALK_BEGIN_MANUAL",
        "HJFLPAICAEO": false,
        "HNFEAICLPLM": [],
        "HPPIPDNHFJG": false,
        "IBGGIIDBOAG": false,
        "IEFDIICFIJK": 201040101,
        "ILHDCGDKKKA": "TALK_HERO_MAIN",
        "ILHDNJDDEOP": 2010401,
        "JGFEJPBPHGJ": [],
        "JNFAMBOFGHJ": false,
        "KINCAGMDMHH": [
          1596
        ],
        "KJLNGKKBBOI": "TALK_MARK_NONE",
        "KNBDEPPFNBN": 0,
        "LCIDOOMOIPM": 0,
        "LIJPPLJCHGI": 0,
        "LMAPLNHKPOH": [],
        "MBDOOOMPFCD": false,
        "MEGMNOELHAO": false,
        "MMCFFPNNDDP": false,
        "MOAKNHNKCON": 0,
        "MOFGBFLPGDM": [],
        "NGNGBPOHNJF": [
          {
            "_param": [
              "2010401",
              "2"
            ],
            "_type": "QUEST_COND_STATE_EQUAL"
          }
        ],
        "NIJAPEJKLDI": false,
        "NMKNFLIHHHE": false,
        "NMMOKMEKDJO": false,
        "NPGONNBAOOI": 14736216968870015911,
        "OAIIIMFGNGM": false,
        "OAOCMNEPKOG": 20104,
        "ODEOIJMOMPL": [],
        "OMLNDCDBHEO": false,
        "PBFMFECIGDG": "TALK_NORMAL_QUEST",
        "PCCKKGAHFFJ": false,
        "PNACKFKJJHM": []
      },
      {
        "<DLGBBMLABOA>k__BackingField": 0,
        "ABDCADBLCFC": 0,
        "AIMIPKGBAHC": "",
        "ANDJNFLIDIJ": "PLAY_MODE_ALL",
        "AOLKCANJCMJ": 3,
        "BKDENCDKDEE": "",
        "BPIIFMJLJAJ": [],
        "DAMGEPEMGNO": false,
        "DBACCKDPONG": [],
        "DIAFFIANKPH": false,
        "DKOMBMCJMMN": false,
        "EFBOKHEHKJM": [],
        "EIDINNIHMHD": false,
        "EKANPNMEFMG": [],
        "ENDBMMDPPAH": [],
        "FALLCBHGKON": "LOGIC_AND",
        "GEPGLHFDBNF": [],
        "GLJMLHNKKKO": "TALK_BEGIN_MANUAL",
        "HJFLPAICAEO": false,
        "HNFEAICLPLM": [],
        "HPPIPDNHFJG": false,
        "IBGGIIDBOAG": false,
        "IEFDIICFIJK": 201040201,
        "ILHDCGDKKKA": "TALK_HERO_MAIN",
        "ILHDNJDDEOP": 2010402,
        "JGFEJPBPHGJ": [],
        "JNFAMBOFGHJ": false,
        "KINCAGMDMHH": [
          1596
        ],
        "KJLNGKKBBOI": "TALK_MARK_NONE",
        "KNBDEPPFNBN": 0,
        "LCIDOOMOIPM": 0,
        "LIJPPLJCHGI": 0,
        "LMAPLNHKPOH": [],
        "MBDOOOMPFCD": false,
        "MEGMNOELHAO": false,
        "MMCFFPNNDDP": false,
        "MOAKNHNKCON": 0,
        "MOFGBFLPGDM": [],
        "NGNGBPOHNJF": [
          {
            "_param": [
              "2010404",
              "2"
            ],
            "_type": "QUEST_COND_STATE_EQUAL"
          },
          {
            "_param": [
              "2010402",
              "3"
            ],
            "_type": "QUEST_COND_STATE_EQUAL"
          }
        ],
        "NIJAPEJKLDI": false,
        "NMKNFLIHHHE": false,
        "NMMOKMEKDJO": false,
        "NPGONNBAOOI": 4159706556906482979,
        "OAIIIMFGNGM": false,
        "OAOCMNEPKOG": 20104,
        "ODEOIJMOMPL": [],
        "OMLNDCDBHEO": false,
        "PBFMFECIGDG": "TALK_NORMAL_QUEST",
        "PCCKKGAHFFJ": false,
        "PNACKFKJJHM": []
      },
      {
        "<DLGBBMLABOA>k__BackingField": 0,
        "ABDCADBLCFC": 0,
        "AIMIPKGBAHC": "",
        "ANDJNFLIDIJ": "PLAY_MODE_ALL",
        "AOLKCANJCMJ": 5,
        "BKDENCDKDEE": "",
        "BPIIFMJLJAJ": [],
        "DAMGEPEMGNO": false,
        "DBACCKDPONG": [],
        "DIAFFIANKPH": false,
        "DKOMBMCJMMN": false,
        "EFBOKHEHKJM": [],
        "EIDINNIHMHD": false,
        "EKANPNMEFMG": [],
        "ENDBMMDPPAH": [],
        "FALLCBHGKON": "LOGIC_AND",
        "GEPGLHFDBNF": [],
        "GLJMLHNKKKO": "TALK_BEGIN_MANUAL",
        "HJFLPAICAEO": false,
        "HNFEAICLPLM": [],
        "HPPIPDNHFJG": false,
        "IBGGIIDBOAG": false,
        "IEFDIICFIJK": 201040301,
        "ILHDCGDKKKA": "TALK_HERO_MAIN",
        "ILHDNJDDEOP": 2010403,
        "JGFEJPBPHGJ": [],
        "JNFAMBOFGHJ": false,
        "KINCAGMDMHH": [
          1596
        ],
        "KJLNGKKBBOI": "TALK_MARK_NONE",
        "KNBDEPPFNBN": 0,
        "LCIDOOMOIPM": 0,
        "LIJPPLJCHGI": 0,
        "LMAPLNHKPOH": [],
        "MBDOOOMPFCD": false,
        "MEGMNOELHAO": false,
        "MMCFFPNNDDP": false,
        "MOAKNHNKCON": 0,
        "MOFGBFLPGDM": [],
        "NGNGBPOHNJF": [
          {
            "_param": [
              "2010404",
              "2"
            ],
            "_type": "QUEST_COND_STATE_EQUAL"
          },
          {
            "_param": [
              "2010403",
              "3"
            ],
            "_type": "QUEST_COND_STATE_EQUAL"
          }
        ],
        "NIJAPEJKLDI": false,
        "NMKNFLIHHHE": false,
        "NMMOKMEKDJO": false,
        "NPGONNBAOOI": 6739916943893923047,
        "OAIIIMFGNGM": false,
        "OAOCMNEPKOG": 20104,
        "ODEOIJMOMPL": [],
        "OMLNDCDBHEO": false,
        "PBFMFECIGDG": "TALK_NORMAL_QUEST",
        "PCCKKGAHFFJ": false,
        "PNACKFKJJHM": []
      },
      {
        "<DLGBBMLABOA>k__BackingField": 0,
        "ABDCADBLCFC": 0,
        "AIMIPKGBAHC": "",
        "ANDJNFLIDIJ": "PLAY_MODE_ALL",
        "AOLKCANJCMJ": 0,
        "BKDENCDKDEE": "",
        "BPIIFMJLJAJ": [],
        "DAMGEPEMGNO": false,
        "DBACCKDPONG": [],
        "DIAFFIANKPH": false,
        "DKOMBMCJMMN": false,
        "EFBOKHEHKJM": [],
        "EIDINNIHMHD": false,
        "EKANPNMEFMG": [],
        "ENDBMMDPPAH": [],
        "FALLCBHGKON": "LOGIC_NONE",
        "GEPGLHFDBNF": [],
        "GLJMLHNKKKO": "TALK_BEGIN_MANUAL",
        "HJFLPAICAEO": false,
        "HNFEAICLPLM": [],
        "HPPIPDNHFJG": false,
        "IBGGIIDBOAG": false,
        "IEFDIICFIJK": 201040501,
        "ILHDCGDKKKA": "TALK_HERO_MAIN",
        "ILHDNJDDEOP": 2010405,
        "JGFEJPBPHGJ": [],
        "JNFAMBOFGHJ": false,
        "KINCAGMDMHH": [
          1596
        ],
        "KJLNGKKBBOI": "TALK_MARK_NONE",
        "KNBDEPPFNBN": 0,
        "LCIDOOMOIPM": 0,
        "LIJPPLJCHGI": 0,
        "LMAPLNHKPOH": [],
        "MBDOOOMPFCD": false,
        "MEGMNOELHAO": false,
        "MMCFFPNNDDP": false,
        "MOAKNHNKCON": 0,
        "MOFGBFLPGDM": [],
        "NGNGBPOHNJF": [
          {
            "_param": [
              "2010402",
              "2"
            ],
            "_type": "QUEST_COND_STATE_EQUAL"
          }
        ],
        "NIJAPEJKLDI": false,
        "NMKNFLIHHHE": false,
        "NMMOKMEKDJO": false,
        "NPGONNBAOOI": 348856166090319760,
        "OAIIIMFGNGM": false,
        "OAOCMNEPKOG": 20104,
        "ODEOIJMOMPL": [],
        "OMLNDCDBHEO": false,
        "PBFMFECIGDG": "TALK_NORMAL_QUEST",
        "PCCKKGAHFFJ": false,
        "PNACKFKJJHM": []
      },
      {
        "<DLGBBMLABOA>k__BackingField": 0,
        "ABDCADBLCFC": 0,
        "AIMIPKGBAHC": "",
        "ANDJNFLIDIJ": "PLAY_MODE_ALL",
        "AOLKCANJCMJ": 0,
        "BKDENCDKDEE": "",
        "BPIIFMJLJAJ": [],
        "DAMGEPEMGNO": false,
        "DBACCKDPONG": [],
        "DIAFFIANKPH": false,
        "DKOMBMCJMMN": false,
        "EFBOKHEHKJM": [],
        "EIDINNIHMHD": false,
        "EKANPNMEFMG": [],
        "ENDBMMDPPAH": [],
        "FALLCBHGKON": "LOGIC_NONE",
        "GEPGLHFDBNF": [],
        "GLJMLHNKKKO": "TALK_BEGIN_MANUAL",
        "HJFLPAICAEO": false,
        "HNFEAICLPLM": [],
        "HPPIPDNHFJG": false,
        "IBGGIIDBOAG": false,
        "IEFDIICFIJK": 201040601,
        "ILHDCGDKKKA": "TALK_HERO_MAIN",
        "ILHDNJDDEOP": 2010406,
        "JGFEJPBPHGJ": [],
        "JNFAMBOFGHJ": false,
        "KINCAGMDMHH": [
          1595
        ],
        "KJLNGKKBBOI": "TALK_MARK_NONE",
        "KNBDEPPFNBN": 0,
        "LCIDOOMOIPM": 0,
        "LIJPPLJCHGI": 0,
        "LMAPLNHKPOH": [],
        "MBDOOOMPFCD": false,
        "MEGMNOELHAO": false,
        "MMCFFPNNDDP": false,
        "MOAKNHNKCON": 0,
        "MOFGBFLPGDM": [],
        "NGNGBPOHNJF": [
          {
            "_param": [
              "2010402",
              "2"
            ],
            "_type": "QUEST_COND_STATE_EQUAL"
          }
        ],
        "NIJAPEJKLDI": false,
        "NMKNFLIHHHE": false,
        "NMMOKMEKDJO": false,
        "NPGONNBAOOI": 13596164742899516917,
        "OAIIIMFGNGM": false,
        "OAOCMNEPKOG": 20104,
        "ODEOIJMOMPL": [],
        "OMLNDCDBHEO": false,
        "PBFMFECIGDG": "TALK_NORMAL_QUEST",
        "PCCKKGAHFFJ": false,
        "PNACKFKJJHM": []
      }
    ],
    "IBNCKLKHAKG": 0,
    "IEGCPJALJOA": 0,
    "IELNANBAMLH": "QUEST_PAUSE_RES_DESTROY_NONE",
    "ILHDNJDDEOP": 20104,
    "ILICEMABDDI": [],
    "JAPLGJLDPHJ": [],
    "JDCIPCDDDPK": 0,
    "JDEFCNEDMLL": 0,
    "KCONOGOIGIH": 24200,
    "LEFIHLHODBM": [],
    "LMCFKPMJGEO": false,
    "MEJIMPLKPHN": 0,
    "MHHFFHCLDKI": false,
    "MMOEEOFGHHG": 1518501975,
    "NJGLJLODPBN": false,
    "NKAKCKAJCLD": 0,
    "NOCNCPAGOPC": "Actor/Quest/IQ20104",
    "OPIDGNOCOHD": "QUEST_SHOW",
    "PAINLIBBLDK": "IQ",
    "PEDANLIDLGE": 0,
    "PEFIFLDHPEE": false,
    "PIGICJKACHG": [],
    "PPJLLGCPCOL": {
      "HDHKBHOLGIM": {}
    }
  },
  "meta": {
    "questType": "IQ",
    "series": 0,
    "mainQuestTag": "MAINQUEST_TAG_NONE",
    "showType": "QUEST_SHOW",
    "repeatable": true,
    "recommendLevel": 0,
    "chapterId": 0,
    "chapterTitle": "",
    "chapterNum": "",
    "needPlayerLevel": null,
    "cityId": null,
    "cityName": "",
    "unlockDesc": "",
    "preMainQuestIds": [],
    "nextMainQuestIds": [],
    "rewardIdList": [],
    "rewards": []
  }
}