{
  "mainQuestId": 75254,
  "title": "(test)隐藏$HIDDEN",
  "description": "(test)隐藏$HIDDEN",
  "titleTextMapHash": 3250151839,
  "descTextMapHash": 3176933110,
  "mainQuestExcel": {
    "mainQuestId": 75254,
    "titleTextMapHash": 3250151839,
    "title": "(test)隐藏$HIDDEN",
    "descTextMapHash": 3176933110,
    "description": "(test)隐藏$HIDDEN",
    "chapterId": 0,
    "mainQuestTag": "MAINQUEST_TAG_NONE",
    "activeMode": "PLAY_MODE_ALL",
    "activityId": 0,
    "luaPath": "Actor/Quest/WQ75254",
    "mainQuestRaw": {
      "activeMode": "PLAY_MODE_ALL",
      "activityId": 0,
      "chapterId": 0,
      "descTextMapHash": 3176933110,
      "EPJHBBICPCA": true,
      "FFOAGHNMJKJ": 0,
      "FNFALGGACGA": "",
      "FOKHPBAGMPB": "",
      "GMENNHMBBOH": [
        {
          "actionType": "NONE",
          "id": 0
        },
        {
          "actionType": "NONE",
          "id": 0
        },
        {
          "actionType": "NONE",
          "id": 0
        },
        {
          "actionType": "NONE",
          "id": 0
        },
        {
          "actionType": "NONE",
          "id": 0
        },
        {
          "actionType": "NONE",
          "id": 0
        },
        {
          "actionType": "NONE",
          "id": 0
        },
        {
          "actionType": "NONE",
          "id": 0
        }
      ],
      "id": 75254,
      "IELNANBAMLH": "QUEST_PAUSE_RES_DESTROY_CLIENT_ONLY",
      "IGHALKGCHAB": 3776494425,
      "LEFIHLHODBM": [],
      "luaPath": "Actor/Quest/WQ75254",
      "mainQuestTag": "MAINQUEST_TAG_NONE",
      "MHHFFHCLDKI": false,
      "PEDANLIDLGE": 0,
      "PEFIFLDHPEE": false,
      "recommendLevel": 0,
      "repeatable": false,
      "resId": 0,
      "rewardIdList": [],
      "series": 0,
      "showRedPoint": false,
      "showType": "QUEST_HIDDEN",
      "specialShowCondIdList": [],
      "specialShowQuestId": 0,
      "specialShowRewardId": [],
      "suggestTrackMainQuestList": [],
      "suggestTrackOutOfOrder": false,
      "taskID": 0,
      "titleTextMapHash": 3250151839,
      "type": "WQ",
      "unlockDescTextMapHash": 2586537158
    }
  },
  "flow": [
    {
      "subQuestId": 7525401,
      "order": 1,
      "stepDescription": "(test)隐藏$HIDDEN",
      "stepDescTextMapHash": 2248540292,
      "finishConds": [
        {
          "BFGALAINLMD": 0,
          "LNHLPKELCAL": [
            7525403,
            0
          ],
          "PAINLIBBLDK": "QUEST_CONTENT_COMPLETE_TALK",
          "PPFLKMOMKAI": ""
        }
      ],
      "guide": {
        "BEALNDJFMMC": "QUEST_GUIDE_IN_SCENE_STYLE_NONE",
        "BJKFMDGPIBN": "QUEST_GUIDE_INDICATOR_STYLE_NONE",
        "CCLPMCLNLBJ": "NONE",
        "CJHEDKCIHPA": 0,
        "EMAIGPLHEJH": "QUEST_GUIDE_LAYER_SCENE",
        "GGJOHCAJAPP": 0,
        "HFNCMGLBNGO": "",
        "IDLNFDCEJLG": "QUEST_GUIDE_AREA_STYLE_DEFAULT",
        "KCFINIEBBBG": 0,
        "KEDGDANLBHP": "",
        "KNMAMMFJAOB": "QUEST_GUIDE_STYLE_TARGET",
        "LNHLPKELCAL": [
          "6512"
        ],
        "NOCCOBOFKHP": 3,
        "OFEBJNGBEPL": "QUEST_GUIDE_AUTO_NONE",
        "PAINLIBBLDK": "QUEST_GUIDE_NPC"
      },
      "isHidden": false,
      "talkIds": [
        7525401,
        7525403,
        7525404,
        7525405,
        7525406,
        7525407
      ],
      "talks": [
        {
          "talkId": 7525401,
          "talkConfig": {
            "checkActionAfter": false,
            "crowdLOD0List": [],
            "decoratorID": 0,
            "disableTalkReview": false,
            "dontBlockDaily": false,
            "enableCameraDisplacement": false,
            "extraLoadMarkId": [],
            "finishExec": [
              {
                "param": [
                  "",
                  "",
                  "",
                  "",
                  ""
                ],
                "type": "TALK_EXEC_NONE"
              },
              {
                "param": [
                  "",
                  "",
                  "",
                  "",
                  ""
                ],
                "type": "TALK_EXEC_NONE"
              },
              {
                "param": [
                  "",
                  "",
                  "",
                  "",
                  ""
                ],
                "type": "TALK_EXEC_NONE"
              },
              {
                "param": [
                  "",
                  "",
                  "",
                  "",
                  ""
                ],
                "type": "TALK_EXEC_NONE"
              },
              {
                "param": [
                  "",
                  "",
                  "",
                  "",
                  ""
                ],
                "type": "TALK_EXEC_NONE"
              }
            ],
            "forceNpcNotDestroy": false,
            "heroRuleId": 0,
            "ignoreDragonTalkRule": false,
            "isEnableNoBlackInter": false,
            "linkBehaviorGrpId": 0,
            "loadType": "TALK_NORMAL_QUEST",
            "lockGameTime": false,
            "lowPriority": false,
            "newTalkFinishTime": false,
            "onlyQuestNpc": true,
            "participantId": [],
            "prePerformCfg": "",
            "questIdleTalk": false,
            "randomTalkPos": 0,
            "randomTalkPriorityList": [],
            "removeDuplicatedRandomTalk": false,
            "stayFreeStyle": false,
            "talkMarkHideList": [],
            "talkMarkType": "TALK_MARK_NONE",
            "activeMode": "PLAY_MODE_HOST",
            "beginCond": [
              {
                "param": [
                  "7525401",
                  "2",
                  "",
                  "",
                  ""
                ],
                "type": "QUEST_COND_STATE_EQUAL"
              },
              {
                "param": [
                  "",
                  "",
                  "",
                  "",
                  ""
                ],
                "type": "QUEST_COND_NONE"
              },
              {
                "param": [
                  "",
                  "",
                  "",
                  "",
                  ""
                ],
                "type": "QUEST_COND_NONE"
              },
              {
                "param": [
                  "",
                  "",
                  "",
                  "",
                  ""
                ],
                "type": "QUEST_COND_NONE"
              },
              {
                "param": [
                  "",
                  "",
                  "",
                  "",
                  ""
                ],
                "type": "QUEST_COND_NONE"
              },
              {
                "param": [
                  "",
                  "",
                  "",
                  "",
                  ""
                ],
                "type": "QUEST_COND_NONE"
              },
              {
                "param": [
                  "",
                  "",
                  "",
                  "",
                  ""
                ],
                "type": "QUEST_COND_NONE"
              },
              {
                "param": [
                  "",
                  "",
                  "",
                  "",
                  ""
                ],
                "type": "QUEST_COND_NONE"
              },
              {
                "param": [
                  "",
                  "",
                  "",
                  "",
                  ""
                ],
                "type": "QUEST_COND_NONE"
              },
              {
                "param": [
                  "",
                  "",
                  "",
                  "",
                  ""
                ],
                "type": "QUEST_COND_NONE"
              }
            ],
            "beginCondComb": "LOGIC_NONE",
            "beginWay": "TALK_BEGIN_MANUAL",
            "heroTalk": "TALK_HERO_LOCAL",
            "id": 7525401,
            "initDialog": 752540101,
            "nextRandomTalks": [],
            "nextTalks": [
              7525405,
              7525406
            ],
            "npcId": [
              6512
            ],
            "performCfg": "",
            "priority": 5,
            "questId": 75254,
            "showRandomTalkCount": 0
          },
          "dialogs": [
            {
              "nodeId": 752540101,
              "roleType": "TALK_ROLE_NPC",
              "speakerId": 6512,
              "speakerName": "泰克胡",
              "textMapHash": 2283562498,
              "text": "嚯，朋友！欢迎来到梦中的帕依提提——提提岛！",
              "nextNodeIds": [
                752540102
              ]
            },
            {
              "nodeId": 752540102,
              "roleType": "TALK_ROLE_NPC",
              "speakerId": 6512,
              "speakerName": "泰克胡",
              "textMapHash": 3283379554,
              "text": "往前走就是「醅蜜」酒吧和「尝露」酒吧，我是酒吧的迎宾泰克胡。",
              "nextNodeIds": []
            }
          ]
        },
        {
          "talkId": 7525403,
          "talkConfig": {
            "checkActionAfter": false,
            "crowdLOD0List": [],
            "decoratorID": 0,
            "disableTalkReview": false,
            "dontBlockDaily": false,
            "enableCameraDisplacement": false,
            "extraLoadMarkId": [],
            "finishExec": [
              {
                "param": [
                  "",
                  "",
                  "",
                  "",
                  ""
                ],
                "type": "TALK_EXEC_NONE"
              },
              {
                "param": [
                  "",
                  "",
                  "",
                  "",
                  ""
                ],
                "type": "TALK_EXEC_NONE"
              },
              {
                "param": [
                  "",
                  "",
                  "",
                  "",
                  ""
                ],
                "type": "TALK_EXEC_NONE"
              },
              {
                "param": [
                  "",
                  "",
                  "",
                  "",
                  ""
                ],
                "type": "TALK_EXEC_NONE"
              },
              {
                "param": [
                  "",
                  "",
                  "",
                  "",
                  ""
                ],
                "type": "TALK_EXEC_NONE"
              }
            ],
            "forceNpcNotDestroy": false,
            "heroRuleId": 0,
            "ignoreDragonTalkRule": false,
            "isEnableNoBlackInter": false,
            "linkBehaviorGrpId": 0,
            "loadType": "TALK_NORMAL_QUEST",
            "lockGameTime": false,
            "lowPriority": false,
            "newTalkFinishTime": false,
            "onlyQuestNpc": true,
            "participantId": [],
            "prePerformCfg": "",
            "questIdleTalk": false,
            "randomTalkPos": 0,
            "randomTalkPriorityList": [],
            "removeDuplicatedRandomTalk": false,
            "stayFreeStyle": false,
            "talkMarkHideList": [],
            "talkMarkType": "TALK_MARK_NONE",
            "activeMode": "PLAY_MODE_HOST",
            "beginCond": [
              {
                "param": [
                  "7525401",
                  "2",
                  "",
                  "",
                  ""
                ],
                "type": "QUEST_COND_STATE_EQUAL"
              },
              {
                "param": [
                  "",
                  "",
                  "",
                  "",
                  ""
                ],
                "type": "QUEST_COND_NONE"
              },
              {
                "param": [
                  "",
                  "",
                  "",
                  "",
                  ""
                ],
                "type": "QUEST_COND_NONE"
              },
              {
                "param": [
                  "",
                  "",
                  "",
                  "",
                  ""
                ],
                "type": "QUEST_COND_NONE"
              },
              {
                "param": [
                  "",
                  "",
                  "",
                  "",
                  ""
                ],
                "type": "QUEST_COND_NONE"
              },
              {
                "param": [
                  "",
                  "",
                  "",
                  "",
                  ""
                ],
                "type": "QUEST_COND_NONE"
              },
              {
                "param": [
                  "",
                  "",
                  "",
                  "",
                  ""
                ],
                "type": "QUEST_COND_NONE"
              },
              {
                "param": [
                  "",
                  "",
                  "",
                  "",
                  ""
                ],
                "type": "QUEST_COND_NONE"
              },
              {
                "param": [
                  "",
                  "",
                  "",
                  "",
                  ""
                ],
                "type": "QUEST_COND_NONE"
              },
              {
                "param": [
                  "",
                  "",
                  "",
                  "",
                  ""
                ],
                "type": "QUEST_COND_NONE"
              }
            ],
            "beginCondComb": "LOGIC_NONE",
            "beginWay": "TALK_BEGIN_MANUAL",
            "heroTalk": "TALK_HERO_LOCAL",
            "id": 7525403,
            "initDialog": 752540309,
            "nextRandomTalks": [],
            "nextTalks": [],
            "npcId": [
              6512
            ],
            "performCfg": "",
            "priority": 2,
            "questId": 75254,
            "showRandomTalkCount": 0
          },
          "dialogs": [
            {
              "nodeId": 752540309,
              "roleType": "TALK_ROLE_PLAYER",
              "speakerId": null,
              "speakerName": "旅行者",
              "textMapHash": 1923194578,
              "text": "好吧，那你的眼睛是怎么回事？",
              "nextNodeIds": [
                752540310
              ]
            },
            {
              "nodeId": 752540310,
              "roleType": "TALK_ROLE_NPC",
              "speakerId": 6512,
              "speakerName": "泰克胡",
              "textMapHash": 137226914,
              "text": "哼哼，是一个光头干的，他在我身上留下了这印迹…他现在也在这个岛上，哼，我会好好「感谢」他的。",
              "nextNodeIds": [
                752540311
              ]
            },
            {
              "nodeId": 752540311,
              "roleType": "TALK_ROLE_NPC",
              "speakerId": 6512,
              "speakerName": "泰克胡",
              "textMapHash": 4258474330,
              "text": "我知道听了我的故事，您一定也想为我复仇吧？但不必了！",
              "nextNodeIds": [
                752540312
              ]
            },
            {
              "nodeId": 752540312,
              "roleType": "TALK_ROLE_NPC",
              "speakerId": 6512,
              "speakerName": "泰克胡",
              "textMapHash": 3527890778,
              "text": "亲爱的朋友，在这个如此美丽的夏日，没有人应该感到悲伤。",
              "nextNodeIds": [
                752540313
              ]
            },
            {
              "nodeId": 752540313,
              "roleType": "TALK_ROLE_NPC",
              "speakerId": 6512,
              "speakerName": "泰克胡",
              "textMapHash": 3395608426,
              "text": "请享用我为每位客人准备的欢迎果汁，尽情挥霍这段休闲的时光吧。",
              "nextNodeIds": [
                752540314
              ]
            },
            {
              "nodeId": 752540314,
              "roleType": "TALK_ROLE_NPC",
              "speakerId": 6512,
              "speakerName": "泰克胡",
              "textMapHash": 1246586138,
              "text": "果汁就在那边的橱柜上。",
              "nextNodeIds": []
            }
          ]
        },
        {
          "talkId": 7525404,
          "talkConfig": {
            "checkActionAfter": false,
            "crowdLOD0List": [],
            "decoratorID": 0,
            "disableTalkReview": false,
            "dontBlockDaily": false,
            "enableCameraDisplacement": false,
            "extraLoadMarkId": [],
            "finishExec": [
              {
                "param": [
                  "",
                  "",
                  "",
                  "",
                  ""
                ],
                "type": "TALK_EXEC_NONE"
              },
              {
                "param": [
                  "",
                  "",
                  "",
                  "",
                  ""
                ],
                "type": "TALK_EXEC_NONE"
              },
              {
                "param": [
                  "",
                  "",
                  "",
                  "",
                  ""
                ],
                "type": "TALK_EXEC_NONE"
              },
              {
                "param": [
                  "",
                  "",
                  "",
                  "",
                  ""
                ],
                "type": "TALK_EXEC_NONE"
              },
              {
                "param": [
                  "",
                  "",
                  "",
                  "",
                  ""
                ],
                "type": "TALK_EXEC_NONE"
              }
            ],
            "forceNpcNotDestroy": false,
            "heroRuleId": 0,
            "ignoreDragonTalkRule": false,
            "isEnableNoBlackInter": false,
            "linkBehaviorGrpId": 0,
            "loadType": "TALK_NORMAL_QUEST",
            "lockGameTime": false,
            "lowPriority": false,
            "newTalkFinishTime": false,
            "onlyQuestNpc": true,
            "participantId": [],
            "prePerformCfg": "",
            "questIdleTalk": false,
            "randomTalkPos": 0,
            "randomTalkPriorityList": [],
            "removeDuplicatedRandomTalk": false,
            "stayFreeStyle": false,
            "talkMarkHideList": [],
            "talkMarkType": "TALK_MARK_NONE",
            "activeMode": "PLAY_MODE_HOST",
            "beginCond": [
              {
                "param": [
                  "7525401",
                  "2",
                  "",
                  "",
                  ""
                ],
                "type": "QUEST_COND_STATE_EQUAL"
              },
              {
                "param": [
                  "",
                  "",
                  "",
                  "",
                  ""
                ],
                "type": "QUEST_COND_NONE"
              },
              {
                "param": [
                  "",
                  "",
                  "",
                  "",
                  ""
                ],
                "type": "QUEST_COND_NONE"
              },
              {
                "param": [
                  "",
                  "",
                  "",
                  "",
                  ""
                ],
                "type": "QUEST_COND_NONE"
              },
              {
                "param": [
                  "",
                  "",
                  "",
                  "",
                  ""
                ],
                "type": "QUEST_COND_NONE"
              },
              {
                "param": [
                  "",
                  "",
                  "",
                  "",
                  ""
                ],
                "type": "QUEST_COND_NONE"
              },
              {
                "param": [
                  "",
                  "",
                  "",
                  "",
                  ""
                ],
                "type": "QUEST_COND_NONE"
              },
              {
                "param": [
                  "",
                  "",
                  "",
                  "",
                  ""
                ],
                "type": "QUEST_COND_NONE"
              },
              {
                "param": [
                  "",
                  "",
                  "",
                  "",
                  ""
                ],
                "type": "QUEST_COND_NONE"
              },
              {
                "param": [
                  "",
                  "",
                  "",
                  "",
                  ""
                ],
                "type": "QUEST_COND_NONE"
              }
            ],
            "beginCondComb": "LOGIC_NONE",
            "beginWay": "TALK_BEGIN_MANUAL",
            "heroTalk": "TALK_HERO_LOCAL",
            "id": 7525404,
            "initDialog": 752540409,
            "nextRandomTalks": [],
            "nextTalks": [],
            "npcId": [
              6512
            ],
            "performCfg": "",
            "priority": 2,
            "questId": 75254,
            "showRandomTalkCount": 0
          },
          "dialogs": [
            {
              "nodeId": 752540409,
              "roleType": "TALK_ROLE_PLAYER",
              "speakerId": null,
              "speakerName": "旅行者",
              "textMapHash": 2776889026,
              "text": "再见。",
              "nextNodeIds": [
                752540410
              ]
            },
            {
              "nodeId": 752540410,
              "roleType": "TALK_ROLE_NPC",
              "speakerId": 6512,
              "speakerName": "泰克胡",
              "textMapHash": 3871825610,
              "text": "你还没问我的眼睛是怎么回事呢…",
              "nextNodeIds": []
            }
          ]
        },
        {
          "talkId": 7525405,
          "talkConfig": {
            "checkActionAfter": false,
            "crowdLOD0List": [],
            "decoratorID": 0,
            "disableTalkReview": false,
            "dontBlockDaily": false,
            "enableCameraDisplacement": false,
            "extraLoadMarkId": [],
            "finishExec": [
              {
                "param": [
                  "",
                  "",
                  "",
                  "",
                  ""
                ],
                "type": "TALK_EXEC_NONE"
              },
              {
                "param": [
                  "",
                  "",
                  "",
                  "",
                  ""
                ],
                "type": "TALK_EXEC_NONE"
              },
              {
                "param": [
                  "",
                  "",
                  "",
                  "",
                  ""
                ],
                "type": "TALK_EXEC_NONE"
              },
              {
                "param": [
                  "",
                  "",
                  "",
                  "",
                  ""
                ],
                "type": "TALK_EXEC_NONE"
              },
              {
                "param": [
                  "",
                  "",
                  "",
                  "",
                  ""
                ],
                "type": "TALK_EXEC_NONE"
              }
            ],
            "forceNpcNotDestroy": false,
            "heroRuleId": 0,
            "ignoreDragonTalkRule": false,
            "isEnableNoBlackInter": false,
            "linkBehaviorGrpId": 0,
            "loadType": "TALK_NORMAL_QUEST",
            "lockGameTime": false,
            "lowPriority": false,
            "newTalkFinishTime": false,
            "onlyQuestNpc": true,
            "participantId": [],
            "prePerformCfg": "",
            "questIdleTalk": false,
            "randomTalkPos": 0,
            "randomTalkPriorityList": [],
            "removeDuplicatedRandomTalk": false,
            "stayFreeStyle": false,
            "talkMarkHideList": [],
            "talkMarkType": "TALK_MARK_NONE",
            "activeMode": "PLAY_MODE_HOST",
            "beginCond": [
              {
                "param": [
                  "7525401",
                  "2",
                  "",
                  "",
                  ""
                ],
                "type": "QUEST_COND_STATE_EQUAL"
              },
              {
                "param": [
                  "7525205",
                  "3",
                  "",
                  "",
                  ""
                ],
                "type": "QUEST_COND_STATE_EQUAL"
              },
              {
                "param": [
                  "",
                  "",
                  "",
                  "",
                  ""
                ],
                "type": "QUEST_COND_NONE"
              },
              {
                "param": [
                  "",
                  "",
                  "",
                  "",
                  ""
                ],
                "type": "QUEST_COND_NONE"
              },
              {
                "param": [
                  "",
                  "",
                  "",
                  "",
                  ""
                ],
                "type": "QUEST_COND_NONE"
              },
              {
                "param": [
                  "",
                  "",
                  "",
                  "",
                  ""
                ],
                "type": "QUEST_COND_NONE"
              },
              {
                "param": [
                  "",
                  "",
                  "",
                  "",
                  ""
                ],
                "type": "QUEST_COND_NONE"
              },
              {
                "param": [
                  "",
                  "",
                  "",
                  "",
                  ""
                ],
                "type": "QUEST_COND_NONE"
              },
              {
                "param": [
                  "",
                  "",
                  "",
                  "",
                  ""
                ],
                "type": "QUEST_COND_NONE"
              },
              {
                "param": [
                  "",
                  "",
                  "",
                  "",
                  ""
                ],
                "type": "QUEST_COND_NONE"
              }
            ],
            "beginCondComb": "LOGIC_AND",
            "beginWay": "TALK_BEGIN_MANUAL",
            "heroTalk": "TALK_HERO_LOCAL",
            "id": 7525405,
            "initDialog": 752540509,
            "nextRandomTalks": [],
            "nextTalks": [
              7525407
            ],
            "npcId": [
              6512
            ],
            "performCfg": "",
            "priority": 4,
            "questId": 75254,
            "showRandomTalkCount": 0
          },
          "dialogs": [
            {
              "nodeId": 752540509,
              "roleType": "TALK_ROLE_PLAYER",
              "speakerId": null,
              "speakerName": "旅行者",
              "textMapHash": 2009794706,
              "text": "我们好像在哪见过？",
              "nextNodeIds": [
                752540501
              ]
            },
            {
              "nodeId": 752540501,
              "roleType": "TALK_ROLE_NPC",
              "speakerId": 6512,
              "speakerName": "泰克胡",
              "textMapHash": 351153410,
              "text": "朋友，这是命运给不凡之人打上的标记，让您与我初次相遇，也如同久别重逢。",
              "nextNodeIds": [
                752540502
              ]
            },
            {
              "nodeId": 752540502,
              "roleType": "TALK_ROLE_NPC",
              "speakerId": 6512,
              "speakerName": "泰克胡",
              "textMapHash": 3420453330,
              "text": "看到我这恶狼般的眼罩，想必就已经意识到了我的不凡了吧？",
              "nextNodeIds": []
            }
          ]
        },
        {
          "talkId": 7525406,
          "talkConfig": {
            "checkActionAfter": false,
            "crowdLOD0List": [],
            "decoratorID": 0,
            "disableTalkReview": false,
            "dontBlockDaily": false,
            "enableCameraDisplacement": false,
            "extraLoadMarkId": [],
            "finishExec": [
              {
                "param": [
                  "",
                  "",
                  "",
                  "",
                  ""
                ],
                "type": "TALK_EXEC_NONE"
              },
              {
                "param": [
                  "",
                  "",
                  "",
                  "",
                  ""
                ],
                "type": "TALK_EXEC_NONE"
              },
              {
                "param": [
                  "",
                  "",
                  "",
                  "",
                  ""
                ],
                "type": "TALK_EXEC_NONE"
              },
              {
                "param": [
                  "",
                  "",
                  "",
                  "",
                  ""
                ],
                "type": "TALK_EXEC_NONE"
              },
              {
                "param": [
                  "",
                  "",
                  "",
                  "",
                  ""
                ],
                "type": "TALK_EXEC_NONE"
              }
            ],
            "forceNpcNotDestroy": false,
            "heroRuleId": 0,
            "ignoreDragonTalkRule": false,
            "isEnableNoBlackInter": false,
            "linkBehaviorGrpId": 0,
            "loadType": "TALK_NORMAL_QUEST",
            "lockGameTime": false,
            "lowPriority": false,
            "newTalkFinishTime": false,
            "onlyQuestNpc": true,
            "participantId": [],
            "prePerformCfg": "",
            "questIdleTalk": false,
            "randomTalkPos": 0,
            "randomTalkPriorityList": [],
            "removeDuplicatedRandomTalk": false,
            "stayFreeStyle": false,
            "talkMarkHideList": [],
            "talkMarkType": "TALK_MARK_NONE",
            "activeMode": "PLAY_MODE_HOST",
            "beginCond": [
              {
                "param": [
                  "7525401",
                  "2",
                  "",
                  "",
                  ""
                ],
                "type": "QUEST_COND_STATE_EQUAL"
              },
              {
                "param": [
                  "7525205",
                  "3",
                  "",
                  "",
                  ""
                ],
                "type": "QUEST_COND_QUEST_STATE_NOT_EQUAL"
              },
              {
                "param": [
                  "",
                  "",
                  "",
                  "",
                  ""
                ],
                "type": "QUEST_COND_NONE"
              },
              {
                "param": [
                  "",
                  "",
                  "",
                  "",
                  ""
                ],
                "type": "QUEST_COND_NONE"
              },
              {
                "param": [
                  "",
                  "",
                  "",
                  "",
                  ""
                ],
                "type": "QUEST_COND_NONE"
              },
              {
                "param": [
                  "",
                  "",
                  "",
                  "",
                  ""
                ],
                "type": "QUEST_COND_NONE"
              },
              {
                "param": [
                  "",
                  "",
                  "",
                  "",
                  ""
                ],
                "type": "QUEST_COND_NONE"
              },
              {
                "param": [
                  "",
                  "",
                  "",
                  "",
                  ""
                ],
                "type": "QUEST_COND_NONE"
              },
              {
                "param": [
                  "",
                  "",
                  "",
                  "",
                  ""
                ],
                "type": "QUEST_COND_NONE"
              },
              {
                "param": [
                  "",
                  "",
                  "",
                  "",
                  ""
                ],
                "type": "QUEST_COND_NONE"
              }
            ],
            "beginCondComb": "LOGIC_AND",
            "beginWay": "TALK_BEGIN_MANUAL",
            "heroTalk": "TALK_HERO_LOCAL",
            "id": 7525406,
            "initDialog": 752540603,
            "nextRandomTalks": [],
            "nextTalks": [
              7525403,
              7525404
            ],
            "npcId": [
              6512
            ],
            "performCfg": "",
            "priority": 4,
            "questId": 75254,
            "showRandomTalkCount": 0
          },
          "dialogs": [
            {
              "nodeId": 752540603,
              "roleType": "TALK_ROLE_NPC",
              "speakerId": 6512,
              "speakerName": "泰克胡",
              "textMapHash": 752395562,
              "text": "哦？您问我泰克胡的眼睛？哈哈，这是男人一生必须修炼的三件事。",
              "nextNodeIds": [
                752540604
              ]
            },
            {
              "nodeId": 752540604,
              "roleType": "TALK_ROLE_NPC",
              "speakerId": 6512,
              "speakerName": "泰克胡",
              "textMapHash": 4221874194,
              "text": "第一，一具饱经风霜的身体，至少要有一道伤疤，否则就不能暗示这个男人曾经历过的复杂人生，这使他失去厚度。",
              "nextNodeIds": [
                752540605
              ]
            },
            {
              "nodeId": 752540605,
              "roleType": "TALK_ROLE_NPC",
              "speakerId": 6512,
              "speakerName": "泰克胡",
              "textMapHash": 1202414554,
              "text": "第二，用服装或者饰品遮住伤疤，保持低调但不要全部遮住，否则旁人就无法意识到这个男人的特殊。",
              "nextNodeIds": [
                752540606
              ]
            },
            {
              "nodeId": 752540606,
              "roleType": "TALK_ROLE_NPC",
              "speakerId": 6512,
              "speakerName": "泰克胡",
              "textMapHash": 1857427666,
              "text": "第三…",
              "nextNodeIds": [
                752540607
              ]
            },
            {
              "nodeId": 752540607,
              "roleType": "TALK_ROLE_PLAYER",
              "speakerId": null,
              "speakerName": "旅行者",
              "textMapHash": 1914811578,
              "text": "停一下，我根本没有问你的眼睛。",
              "nextNodeIds": [
                752540608
              ]
            },
            {
              "nodeId": 752540608,
              "roleType": "TALK_ROLE_NPC",
              "speakerId": 6512,
              "speakerName": "泰克胡",
              "textMapHash": 3716436762,
              "text": "是吧？没错！这就是我要说的第三点：如果旁人还是没有注意到，一定要想办法主动提起…",
              "nextNodeIds": []
            }
          ]
        },
        {
          "talkId": 7525407,
          "talkConfig": {
            "checkActionAfter": false,
            "crowdLOD0List": [],
            "decoratorID": 0,
            "disableTalkReview": false,
            "dontBlockDaily": false,
            "enableCameraDisplacement": false,
            "extraLoadMarkId": [],
            "finishExec": [
              {
                "param": [
                  "",
                  "",
                  "",
                  "",
                  ""
                ],
                "type": "TALK_EXEC_NONE"
              },
              {
                "param": [
                  "",
                  "",
                  "",
                  "",
                  ""
                ],
                "type": "TALK_EXEC_NONE"
              },
              {
                "param": [
                  "",
                  "",
                  "",
                  "",
                  ""
                ],
                "type": "TALK_EXEC_NONE"
              },
              {
                "param": [
                  "",
                  "",
                  "",
                  "",
                  ""
                ],
                "type": "TALK_EXEC_NONE"
              },
              {
                "param": [
                  "",
                  "",
                  "",
                  "",
                  ""
                ],
                "type": "TALK_EXEC_NONE"
              }
            ],
            "forceNpcNotDestroy": false,
            "heroRuleId": 0,
            "ignoreDragonTalkRule": false,
            "isEnableNoBlackInter": false,
            "linkBehaviorGrpId": 0,
            "loadType": "TALK_NORMAL_QUEST",
            "lockGameTime": false,
            "lowPriority": false,
            "newTalkFinishTime": false,
            "onlyQuestNpc": true,
            "participantId": [],
            "prePerformCfg": "",
            "questIdleTalk": false,
            "randomTalkPos": 0,
            "randomTalkPriorityList": [],
            "removeDuplicatedRandomTalk": false,
            "stayFreeStyle": false,
            "talkMarkHideList": [],
            "talkMarkType": "TALK_MARK_NONE",
            "activeMode": "PLAY_MODE_HOST",
            "beginCond": [
              {
                "param": [
                  "7525401",
                  "2",
                  "",
                  "",
                  ""
                ],
                "type": "QUEST_COND_STATE_EQUAL"
              },
              {
                "param": [
                  "",
                  "",
                  "",
                  "",
                  ""
                ],
                "type": "QUEST_COND_NONE"
              },
              {
                "param": [
                  "",
                  "",
                  "",
                  "",
                  ""
                ],
                "type": "QUEST_COND_NONE"
              },
              {
                "param": [
                  "",
                  "",
                  "",
                  "",
                  ""
                ],
                "type": "QUEST_COND_NONE"
              },
              {
                "param": [
                  "",
                  "",
                  "",
                  "",
                  ""
                ],
                "type": "QUEST_COND_NONE"
              },
              {
                "param": [
                  "",
                  "",
                  "",
                  "",
                  ""
                ],
                "type": "QUEST_COND_NONE"
              },
              {
                "param": [
                  "",
                  "",
                  "",
                  "",
                  ""
                ],
                "type": "QUEST_COND_NONE"
              },
              {
                "param": [
                  "",
                  "",
                  "",
                  "",
                  ""
                ],
                "type": "QUEST_COND_NONE"
              },
              {
                "param": [
                  "",
                  "",
                  "",
                  "",
                  ""
                ],
                "type": "QUEST_COND_NONE"
              },
              {
                "param": [
                  "",
                  "",
                  "",
                  "",
                  ""
                ],
                "type": "QUEST_COND_NONE"
              }
            ],
            "beginCondComb": "LOGIC_NONE",
            "beginWay": "TALK_BEGIN_MANUAL",
            "heroTalk": "TALK_HERO_LOCAL",
            "id": 7525407,
            "initDialog": 752540703,
            "nextRandomTalks": [],
            "nextTalks": [
              7525403,
              7525404
            ],
            "npcId": [
              6512
            ],
            "performCfg": "",
            "priority": 3,
            "questId": 75254,
            "showRandomTalkCount": 0
          },
          "dialogs": [
            {
              "nodeId": 752540703,
              "roleType": "TALK_ROLE_NPC",
              "speakerId": 6512,
              "speakerName": "泰克胡",
              "textMapHash": 2603684842,
              "text": "哦？您问我泰克胡的眼睛？哈哈，这是男人一生必须修炼的三件事。",
              "nextNodeIds": [
                752540704
              ]
            },
            {
              "nodeId": 752540704,
              "roleType": "TALK_ROLE_NPC",
              "speakerId": 6512,
              "speakerName": "泰克胡",
              "textMapHash": 3290772530,
              "text": "第一，一具饱经风霜的身体，至少要有一道伤疤，否则就不能暗示这个男人曾经历过的复杂人生，这使他失去厚度。",
              "nextNodeIds": [
                752540705
              ]
            },
            {
              "nodeId": 752540705,
              "roleType": "TALK_ROLE_NPC",
              "speakerId": 6512,
              "speakerName": "泰克胡",
              "textMapHash": 1204872394,
              "text": "第二，用服装或者饰品遮住伤疤，保持低调但不要全部遮住，否则旁人就无法意识到这个男人的特殊。",
              "nextNodeIds": [
                752540706
              ]
            },
            {
              "nodeId": 752540706,
              "roleType": "TALK_ROLE_NPC",
              "speakerId": 6512,
              "speakerName": "泰克胡",
              "textMapHash": 887075306,
              "text": "第三…",
              "nextNodeIds": [
                752540707
              ]
            },
            {
              "nodeId": 752540707,
              "roleType": "TALK_ROLE_PLAYER",
              "speakerId": null,
              "speakerName": "旅行者",
              "textMapHash": 451352442,
              "text": "停一下，我根本没有问你的眼睛。",
              "nextNodeIds": [
                752540708
              ]
            },
            {
              "nodeId": 752540708,
              "roleType": "TALK_ROLE_NPC",
              "speakerId": 6512,
              "speakerName": "泰克胡",
              "textMapHash": 310072898,
              "text": "是吧？没错！这就是我要说的第三点：如果旁人还是没有注意到，一定要想办法主动提起…",
              "nextNodeIds": []
            }
          ]
        }
      ],
      "conditions": {
        "finishCond": [
          {
            "BFGALAINLMD": 0,
            "LNHLPKELCAL": [
              7525403,
              0
            ],
            "PAINLIBBLDK": "QUEST_CONTENT_COMPLETE_TALK",
            "PPFLKMOMKAI": ""
          }
        ],
        "triggerCond": [],
        "execActions": [
          {
            "LNHLPKELCAL": [
              "3",
              "133522029"
            ],
            "PAINLIBBLDK": "QUEST_EXEC_NOTIFY_GROUP_LUA"
          }
        ],
        "guide": {
          "BEALNDJFMMC": "QUEST_GUIDE_IN_SCENE_STYLE_NONE",
          "BJKFMDGPIBN": "QUEST_GUIDE_INDICATOR_STYLE_NONE",
          "CCLPMCLNLBJ": "NONE",
          "CJHEDKCIHPA": 0,
          "EMAIGPLHEJH": "QUEST_GUIDE_LAYER_SCENE",
          "GGJOHCAJAPP": 0,
          "HFNCMGLBNGO": "",
          "IDLNFDCEJLG": "QUEST_GUIDE_AREA_STYLE_DEFAULT",
          "KCFINIEBBBG": 0,
          "KEDGDANLBHP": "",
          "KNMAMMFJAOB": "QUEST_GUIDE_STYLE_TARGET",
          "LNHLPKELCAL": [
            "6512"
          ],
          "NOCCOBOFKHP": 3,
          "OFEBJNGBEPL": "QUEST_GUIDE_AUTO_NONE",
          "PAINLIBBLDK": "QUEST_GUIDE_NPC"
        }
      }
    },
    {
      "subQuestId": 7525402,
      "order": 2,
      "stepDescription": "(test)隐藏$HIDDEN",
      "stepDescTextMapHash": 1587913892,
      "finishConds": [
        {
          "BFGALAINLMD": 1,
          "LNHLPKELCAL": [
            0,
            0
          ],
          "PAINLIBBLDK": "QUEST_CONTENT_LUA_NOTIFY",
          "PPFLKMOMKAI": "Q7525402DONE"
        }
      ],
      "guide": {
        "BEALNDJFMMC": "QUEST_GUIDE_IN_SCENE_STYLE_NONE",
        "BJKFMDGPIBN": "QUEST_GUIDE_INDICATOR_STYLE_NONE",
        "CCLPMCLNLBJ": "NONE",
        "CJHEDKCIHPA": 0,
        "EMAIGPLHEJH": "QUEST_GUIDE_LAYER_SCENE",
        "GGJOHCAJAPP": 0,
        "HFNCMGLBNGO": "",
        "IDLNFDCEJLG": "QUEST_GUIDE_AREA_STYLE_DEFAULT",
        "KCFINIEBBBG": 0,
        "KEDGDANLBHP": "",
        "KNMAMMFJAOB": "QUEST_GUIDE_STYLE_TARGET",
        "LNHLPKELCAL": [
          "6512"
        ],
        "NOCCOBOFKHP": 3,
        "OFEBJNGBEPL": "QUEST_GUIDE_AUTO_NONE",
        "PAINLIBBLDK": "QUEST_GUIDE_NPC"
      },
      "isHidden": false,
      "talkIds": [],
      "talks": [],
      "conditions": {
        "finishCond": [
          {
            "BFGALAINLMD": 1,
            "LNHLPKELCAL": [
              0,
              0
            ],
            "PAINLIBBLDK": "QUEST_CONTENT_LUA_NOTIFY",
            "PPFLKMOMKAI": "Q7525402DONE"
          }
        ],
        "triggerCond": [],
        "execActions": [],
        "guide": {
          "BEALNDJFMMC": "QUEST_GUIDE_IN_SCENE_STYLE_NONE",
          "BJKFMDGPIBN": "QUEST_GUIDE_INDICATOR_STYLE_NONE",
          "CCLPMCLNLBJ": "NONE",
          "CJHEDKCIHPA": 0,
          "EMAIGPLHEJH": "QUEST_GUIDE_LAYER_SCENE",
          "GGJOHCAJAPP": 0,
          "HFNCMGLBNGO": "",
          "IDLNFDCEJLG": "QUEST_GUIDE_AREA_STYLE_DEFAULT",
          "KCFINIEBBBG": 0,
          "KEDGDANLBHP": "",
          "KNMAMMFJAOB": "QUEST_GUIDE_STYLE_TARGET",
          "LNHLPKELCAL": [
            "6512"
          ],
          "NOCCOBOFKHP": 3,
          "OFEBJNGBEPL": "QUEST_GUIDE_AUTO_NONE",
          "PAINLIBBLDK": "QUEST_GUIDE_NPC"
        }
      }
    },
    {
      "subQuestId": 7525403,
      "order": 3,
      "stepDescription": "(test)隐藏$HIDDEN",
      "stepDescTextMapHash": 286481284,
      "finishConds": [
        {
          "BFGALAINLMD": 0,
          "LNHLPKELCAL": [
            7525402,
            0
          ],
          "PAINLIBBLDK": "QUEST_CONTENT_COMPLETE_TALK",
          "PPFLKMOMKAI": ""
        }
      ],
      "guide": {
        "BEALNDJFMMC": "QUEST_GUIDE_IN_SCENE_STYLE_NONE",
        "BJKFMDGPIBN": "QUEST_GUIDE_INDICATOR_STYLE_NONE",
        "CCLPMCLNLBJ": "NONE",
        "CJHEDKCIHPA": 0,
        "EMAIGPLHEJH": "QUEST_GUIDE_LAYER_SCENE",
        "GGJOHCAJAPP": 0,
        "HFNCMGLBNGO": "",
        "IDLNFDCEJLG": "QUEST_GUIDE_AREA_STYLE_DEFAULT",
        "KCFINIEBBBG": 0,
        "KEDGDANLBHP": "",
        "KNMAMMFJAOB": "QUEST_GUIDE_STYLE_TARGET",
        "LNHLPKELCAL": [
          "6512"
        ],
        "NOCCOBOFKHP": 3,
        "OFEBJNGBEPL": "QUEST_GUIDE_AUTO_NONE",
        "PAINLIBBLDK": "QUEST_GUIDE_NPC"
      },
      "isHidden": false,
      "talkIds": [
        7525402
      ],
      "talks": [
        {
          "talkId": 7525402,
          "talkConfig": {
            "checkActionAfter": false,
            "crowdLOD0List": [],
            "decoratorID": 0,
            "disableTalkReview": false,
            "dontBlockDaily": false,
            "enableCameraDisplacement": false,
            "extraLoadMarkId": [],
            "finishExec": [
              {
                "param": [
                  "",
                  "",
                  "",
                  "",
                  ""
                ],
                "type": "TALK_EXEC_NONE"
              },
              {
                "param": [
                  "",
                  "",
                  "",
                  "",
                  ""
                ],
                "type": "TALK_EXEC_NONE"
              },
              {
                "param": [
                  "",
                  "",
                  "",
                  "",
                  ""
                ],
                "type": "TALK_EXEC_NONE"
              },
              {
                "param": [
                  "",
                  "",
                  "",
                  "",
                  ""
                ],
                "type": "TALK_EXEC_NONE"
              },
              {
                "param": [
                  "",
                  "",
                  "",
                  "",
                  ""
                ],
                "type": "TALK_EXEC_NONE"
              }
            ],
            "forceNpcNotDestroy": false,
            "heroRuleId": 0,
            "ignoreDragonTalkRule": false,
            "isEnableNoBlackInter": false,
            "linkBehaviorGrpId": 0,
            "loadType": "TALK_NORMAL_QUEST",
            "lockGameTime": false,
            "lowPriority": false,
            "newTalkFinishTime": false,
            "onlyQuestNpc": true,
            "participantId": [],
            "prePerformCfg": "",
            "questIdleTalk": false,
            "randomTalkPos": 0,
            "randomTalkPriorityList": [],
            "removeDuplicatedRandomTalk": false,
            "stayFreeStyle": false,
            "talkMarkHideList": [],
            "talkMarkType": "TALK_MARK_NONE",
            "activeMode": "PLAY_MODE_HOST",
            "beginCond": [
              {
                "param": [
                  "7525403",
                  "2",
                  "",
                  "",
                  ""
                ],
                "type": "QUEST_COND_STATE_EQUAL"
              },
              {
                "param": [
                  "",
                  "",
                  "",
                  "",
                  ""
                ],
                "type": "QUEST_COND_NONE"
              },
              {
                "param": [
                  "",
                  "",
                  "",
                  "",
                  ""
                ],
                "type": "QUEST_COND_NONE"
              },
              {
                "param": [
                  "",
                  "",
                  "",
                  "",
                  ""
                ],
                "type": "QUEST_COND_NONE"
              },
              {
                "param": [
                  "",
                  "",
                  "",
                  "",
                  ""
                ],
                "type": "QUEST_COND_NONE"
              },
              {
                "param": [
                  "",
                  "",
                  "",
                  "",
                  ""
                ],
                "type": "QUEST_COND_NONE"
              },
              {
                "param": [
                  "",
                  "",
                  "",
                  "",
                  ""
                ],
                "type": "QUEST_COND_NONE"
              },
              {
                "param": [
                  "",
                  "",
                  "",
                  "",
                  ""
                ],
                "type": "QUEST_COND_NONE"
              },
              {
                "param": [
                  "",
                  "",
                  "",
                  "",
                  ""
                ],
                "type": "QUEST_COND_NONE"
              },
              {
                "param": [
                  "",
                  "",
                  "",
                  "",
                  ""
                ],
                "type": "QUEST_COND_NONE"
              }
            ],
            "beginCondComb": "LOGIC_NONE",
            "beginWay": "TALK_BEGIN_MANUAL",
            "heroTalk": "TALK_HERO_LOCAL",
            "id": 7525402,
            "initDialog": 752540201,
            "nextRandomTalks": [],
            "nextTalks": [],
            "npcId": [
              6512
            ],
            "performCfg": "",
            "priority": 4,
            "questId": 75254,
            "showRandomTalkCount": 0
          },
          "dialogs": [
            {
              "nodeId": 752540201,
              "roleType": "TALK_ROLE_NPC",
              "speakerId": 6512,
              "speakerName": "泰克胡",
              "textMapHash": 2051906970,
              "text": "亲爱的朋友，既然你喝了我的欢迎果汁，那让我给你一个忠告。",
              "nextNodeIds": [
                752540202
              ]
            },
            {
              "nodeId": 752540202,
              "roleType": "TALK_ROLE_NPC",
              "speakerId": 6512,
              "speakerName": "泰克胡",
              "textMapHash": 4148660074,
              "text": "要是你只是个过来享受假期的普通人，那就别靠近提提岛的最北边，那里没有能让你放松的东西。",
              "nextNodeIds": []
            }
          ]
        }
      ],
      "conditions": {
        "finishCond": [
          {
            "BFGALAINLMD": 0,
            "LNHLPKELCAL": [
              7525402,
              0
            ],
            "PAINLIBBLDK": "QUEST_CONTENT_COMPLETE_TALK",
            "PPFLKMOMKAI": ""
          }
        ],
        "triggerCond": [],
        "execActions": [
          {
            "LNHLPKELCAL": [
              "3",
              "133522029"
            ],
            "PAINLIBBLDK": "QUEST_EXEC_NOTIFY_GROUP_LUA"
          }
        ],
        "guide": {
          "BEALNDJFMMC": "QUEST_GUIDE_IN_SCENE_STYLE_NONE",
          "BJKFMDGPIBN": "QUEST_GUIDE_INDICATOR_STYLE_NONE",
          "CCLPMCLNLBJ": "NONE",
          "CJHEDKCIHPA": 0,
          "EMAIGPLHEJH": "QUEST_GUIDE_LAYER_SCENE",
          "GGJOHCAJAPP": 0,
          "HFNCMGLBNGO": "",
          "IDLNFDCEJLG": "QUEST_GUIDE_AREA_STYLE_DEFAULT",
          "KCFINIEBBBG": 0,
          "KEDGDANLBHP": "",
          "KNMAMMFJAOB": "QUEST_GUIDE_STYLE_TARGET",
          "LNHLPKELCAL": [
            "6512"
          ],
          "NOCCOBOFKHP": 3,
          "OFEBJNGBEPL": "QUEST_GUIDE_AUTO_NONE",
          "PAINLIBBLDK": "QUEST_GUIDE_NPC"
        }
      }
    }
  ],
  "unmappedTalks": [],
  "questNarration": [],
  "talkIds": [
    7525401,
    7525402,
    7525403,
    7525404,
    7525405,
    7525406,
    7525407
  ],
  "speakerCounts": [
    {
      "roleType": "TALK_ROLE_NPC",
      "speakerId": 6512,
      "speakerName": "泰克胡",
      "count": 22
    },
    {
      "roleType": "TALK_ROLE_PLAYER",
      "speakerId": null,
      "speakerName": "旅行者",
      "count": 5
    }
  ],
  "raw": {
    "ANDJNFLIDIJ": "PLAY_MODE_ALL",
    "BEGCMMJKCFC": [],
    "BHCBFLFOGJN": 0,
    "BPEIDGPCLGA": false,
    "CBBBCAKOFGO": 3176933110,
    "CHECNJEMEFE": {
      "6512": [
        1200
      ]
    },
    "CJPLOBIFHLG": "MAINQUEST_TAG_NONE",
    "CMDGLJAOFOJ": [],
    "EPJHBBICPCA": true,
    "FBEFCEJCBIK": {},
    "FFOAGHNMJKJ": 0,
    "FNFALGGACGA": "",
    "FOKHPBAGMPB": "",
    "GBFMDJLKJBF": [],
    "GMENNHMBBOH": [],
    "HCJHEADFCAO": 0,
    "IBEGAHMEABP": [
      {
        "<DLGBBMLABOA>k__BackingField": 0,
        "ABDCADBLCFC": 0,
        "AIMIPKGBAHC": "",
        "ANDJNFLIDIJ": "PLAY_MODE_HOST",
        "AOLKCANJCMJ": 5,
        "BKDENCDKDEE": "",
        "BPIIFMJLJAJ": [],
        "DAMGEPEMGNO": false,
        "DBACCKDPONG": [
          7525405,
          7525406
        ],
        "DIAFFIANKPH": false,
        "DKOMBMCJMMN": false,
        "EFBOKHEHKJM": [],
        "EIDINNIHMHD": false,
        "EKANPNMEFMG": [],
        "ENDBMMDPPAH": [],
        "FALLCBHGKON": "LOGIC_NONE",
        "GEPGLHFDBNF": [],
        "GLJMLHNKKKO": "TALK_BEGIN_MANUAL",
        "HJFLPAICAEO": false,
        "HNFEAICLPLM": [],
        "HPPIPDNHFJG": false,
        "IBGGIIDBOAG": false,
        "IEFDIICFIJK": 752540101,
        "ILHDCGDKKKA": "TALK_HERO_LOCAL",
        "ILHDNJDDEOP": 7525401,
        "JGFEJPBPHGJ": [],
        "JNFAMBOFGHJ": false,
        "KINCAGMDMHH": [
          6512
        ],
        "KJLNGKKBBOI": "TALK_MARK_NONE",
        "KNBDEPPFNBN": 0,
        "LCIDOOMOIPM": 0,
        "LIJPPLJCHGI": 0,
        "LMAPLNHKPOH": [
          9000
        ],
        "MBDOOOMPFCD": false,
        "MEGMNOELHAO": false,
        "MMCFFPNNDDP": false,
        "MOAKNHNKCON": 0,
        "MOFGBFLPGDM": [],
        "NGNGBPOHNJF": [
          {
            "_param": [
              "7525401",
              "2"
            ],
            "_type": "QUEST_COND_STATE_EQUAL"
          }
        ],
        "NIJAPEJKLDI": false,
        "NMKNFLIHHHE": true,
        "NMMOKMEKDJO": false,
        "NPGONNBAOOI": 8423455845715385733,
        "OAIIIMFGNGM": false,
        "OAOCMNEPKOG": 75254,
        "ODEOIJMOMPL": [],
        "OMLNDCDBHEO": false,
        "PBFMFECIGDG": "TALK_NORMAL_QUEST",
        "PCCKKGAHFFJ": false,
        "PNACKFKJJHM": []
      },
      {
        "<DLGBBMLABOA>k__BackingField": 0,
        "ABDCADBLCFC": 0,
        "AIMIPKGBAHC": "",
        "ANDJNFLIDIJ": "PLAY_MODE_HOST",
        "AOLKCANJCMJ": 4,
        "BKDENCDKDEE": "",
        "BPIIFMJLJAJ": [],
        "DAMGEPEMGNO": false,
        "DBACCKDPONG": [],
        "DIAFFIANKPH": false,
        "DKOMBMCJMMN": false,
        "EFBOKHEHKJM": [],
        "EIDINNIHMHD": false,
        "EKANPNMEFMG": [],
        "ENDBMMDPPAH": [],
        "FALLCBHGKON": "LOGIC_NONE",
        "GEPGLHFDBNF": [],
        "GLJMLHNKKKO": "TALK_BEGIN_MANUAL",
        "HJFLPAICAEO": false,
        "HNFEAICLPLM": [],
        "HPPIPDNHFJG": false,
        "IBGGIIDBOAG": false,
        "IEFDIICFIJK": 752540201,
        "ILHDCGDKKKA": "TALK_HERO_LOCAL",
        "ILHDNJDDEOP": 7525402,
        "JGFEJPBPHGJ": [],
        "JNFAMBOFGHJ": false,
        "KINCAGMDMHH": [
          6512
        ],
        "KJLNGKKBBOI": "TALK_MARK_NONE",
        "KNBDEPPFNBN": 0,
        "LCIDOOMOIPM": 0,
        "LIJPPLJCHGI": 0,
        "LMAPLNHKPOH": [],
        "MBDOOOMPFCD": false,
        "MEGMNOELHAO": false,
        "MMCFFPNNDDP": false,
        "MOAKNHNKCON": 0,
        "MOFGBFLPGDM": [],
        "NGNGBPOHNJF": [
          {
            "_param": [
              "7525403",
              "2"
            ],
            "_type": "QUEST_COND_STATE_EQUAL"
          }
        ],
        "NIJAPEJKLDI": false,
        "NMKNFLIHHHE": true,
        "NMMOKMEKDJO": false,
        "NPGONNBAOOI": 11249281155085333586,
        "OAIIIMFGNGM": false,
        "OAOCMNEPKOG": 75254,
        "ODEOIJMOMPL": [],
        "OMLNDCDBHEO": false,
        "PBFMFECIGDG": "TALK_NORMAL_QUEST",
        "PCCKKGAHFFJ": false,
        "PNACKFKJJHM": []
      },
      {
        "<DLGBBMLABOA>k__BackingField": 0,
        "ABDCADBLCFC": 0,
        "AIMIPKGBAHC": "",
        "ANDJNFLIDIJ": "PLAY_MODE_HOST",
        "AOLKCANJCMJ": 2,
        "BKDENCDKDEE": "",
        "BPIIFMJLJAJ": [],
        "DAMGEPEMGNO": false,
        "DBACCKDPONG": [],
        "DIAFFIANKPH": false,
        "DKOMBMCJMMN": false,
        "EFBOKHEHKJM": [],
        "EIDINNIHMHD": false,
        "EKANPNMEFMG": [],
        "ENDBMMDPPAH": [],
        "FALLCBHGKON": "LOGIC_NONE",
        "GEPGLHFDBNF": [],
        "GLJMLHNKKKO": "TALK_BEGIN_MANUAL",
        "HJFLPAICAEO": false,
        "HNFEAICLPLM": [],
        "HPPIPDNHFJG": false,
        "IBGGIIDBOAG": false,
        "IEFDIICFIJK": 752540309,
        "ILHDCGDKKKA": "TALK_HERO_LOCAL",
        "ILHDNJDDEOP": 7525403,
        "JGFEJPBPHGJ": [],
        "JNFAMBOFGHJ": false,
        "KINCAGMDMHH": [
          6512
        ],
        "KJLNGKKBBOI": "TALK_MARK_NONE",
        "KNBDEPPFNBN": 0,
        "LCIDOOMOIPM": 0,
        "LIJPPLJCHGI": 0,
        "LMAPLNHKPOH": [],
        "MBDOOOMPFCD": false,
        "MEGMNOELHAO": false,
        "MMCFFPNNDDP": false,
        "MOAKNHNKCON": 0,
        "MOFGBFLPGDM": [],
        "NGNGBPOHNJF": [
          {
            "_param": [
              "7525401",
              "2"
            ],
            "_type": "QUEST_COND_STATE_EQUAL"
          }
        ],
        "NIJAPEJKLDI": false,
        "NMKNFLIHHHE": true,
        "NMMOKMEKDJO": false,
        "NPGONNBAOOI": 17574244158554145350,
        "OAIIIMFGNGM": false,
        "OAOCMNEPKOG": 75254,
        "ODEOIJMOMPL": [],
        "OMLNDCDBHEO": false,
        "PBFMFECIGDG": "TALK_NORMAL_QUEST",
        "PCCKKGAHFFJ": false,
        "PNACKFKJJHM": []
      },
      {
        "<DLGBBMLABOA>k__BackingField": 0,
        "ABDCADBLCFC": 0,
        "AIMIPKGBAHC": "",
        "ANDJNFLIDIJ": "PLAY_MODE_HOST",
        "AOLKCANJCMJ": 2,
        "BKDENCDKDEE": "",
        "BPIIFMJLJAJ": [],
        "DAMGEPEMGNO": false,
        "DBACCKDPONG": [],
        "DIAFFIANKPH": false,
        "DKOMBMCJMMN": false,
        "EFBOKHEHKJM": [],
        "EIDINNIHMHD": false,
        "EKANPNMEFMG": [],
        "ENDBMMDPPAH": [],
        "FALLCBHGKON": "LOGIC_NONE",
        "GEPGLHFDBNF": [],
        "GLJMLHNKKKO": "TALK_BEGIN_MANUAL",
        "HJFLPAICAEO": false,
        "HNFEAICLPLM": [],
        "HPPIPDNHFJG": false,
        "IBGGIIDBOAG": false,
        "IEFDIICFIJK": 752540409,
        "ILHDCGDKKKA": "TALK_HERO_LOCAL",
        "ILHDNJDDEOP": 7525404,
        "JGFEJPBPHGJ": [],
        "JNFAMBOFGHJ": false,
        "KINCAGMDMHH": [
          6512
        ],
        "KJLNGKKBBOI": "TALK_MARK_NONE",
        "KNBDEPPFNBN": 0,
        "LCIDOOMOIPM": 0,
        "LIJPPLJCHGI": 0,
        "LMAPLNHKPOH": [],
        "MBDOOOMPFCD": false,
        "MEGMNOELHAO": false,
        "MMCFFPNNDDP": false,
        "MOAKNHNKCON": 0,
        "MOFGBFLPGDM": [],
        "NGNGBPOHNJF": [
          {
            "_param": [
              "7525401",
              "2"
            ],
            "_type": "QUEST_COND_STATE_EQUAL"
          }
        ],
        "NIJAPEJKLDI": false,
        "NMKNFLIHHHE": true,
        "NMMOKMEKDJO": false,
        "NPGONNBAOOI": 14772883864743178732,
        "OAIIIMFGNGM": false,
        "OAOCMNEPKOG": 75254,
        "ODEOIJMOMPL": [],
        "OMLNDCDBHEO": false,
        "PBFMFECIGDG": "TALK_NORMAL_QUEST",
        "PCCKKGAHFFJ": false,
        "PNACKFKJJHM": []
      },
      {
        "<DLGBBMLABOA>k__BackingField": 0,
        "ABDCADBLCFC": 0,
        "AIMIPKGBAHC": "",
        "ANDJNFLIDIJ": "PLAY_MODE_HOST",
        "AOLKCANJCMJ": 4,
        "BKDENCDKDEE": "",
        "BPIIFMJLJAJ": [],
        "DAMGEPEMGNO": false,
        "DBACCKDPONG": [
          7525407
        ],
        "DIAFFIANKPH": false,
        "DKOMBMCJMMN": false,
        "EFBOKHEHKJM": [],
        "EIDINNIHMHD": false,
        "EKANPNMEFMG": [],
        "ENDBMMDPPAH": [],
        "FALLCBHGKON": "LOGIC_AND",
        "GEPGLHFDBNF": [],
        "GLJMLHNKKKO": "TALK_BEGIN_MANUAL",
        "HJFLPAICAEO": false,
        "HNFEAICLPLM": [],
        "HPPIPDNHFJG": false,
        "IBGGIIDBOAG": false,
        "IEFDIICFIJK": 752540509,
        "ILHDCGDKKKA": "TALK_HERO_LOCAL",
        "ILHDNJDDEOP": 7525405,
        "JGFEJPBPHGJ": [],
        "JNFAMBOFGHJ": false,
        "KINCAGMDMHH": [
          6512
        ],
        "KJLNGKKBBOI": "TALK_MARK_NONE",
        "KNBDEPPFNBN": 0,
        "LCIDOOMOIPM": 0,
        "LIJPPLJCHGI": 0,
        "LMAPLNHKPOH": [
          9000
        ],
        "MBDOOOMPFCD": false,
        "MEGMNOELHAO": false,
        "MMCFFPNNDDP": false,
        "MOAKNHNKCON": 0,
        "MOFGBFLPGDM": [],
        "NGNGBPOHNJF": [
          {
            "_param": [
              "7525401",
              "2"
            ],
            "_type": "QUEST_COND_STATE_EQUAL"
          },
          {
            "_param": [
              "7525205",
              "3"
            ],
            "_type": "QUEST_COND_STATE_EQUAL"
          }
        ],
        "NIJAPEJKLDI": false,
        "NMKNFLIHHHE": true,
        "NMMOKMEKDJO": false,
        "NPGONNBAOOI": 11583775622546016950,
        "OAIIIMFGNGM": false,
        "OAOCMNEPKOG": 75254,
        "ODEOIJMOMPL": [],
        "OMLNDCDBHEO": false,
        "PBFMFECIGDG": "TALK_NORMAL_QUEST",
        "PCCKKGAHFFJ": false,
        "PNACKFKJJHM": []
      },
      {
        "<DLGBBMLABOA>k__BackingField": 0,
        "ABDCADBLCFC": 0,
        "AIMIPKGBAHC": "",
        "ANDJNFLIDIJ": "PLAY_MODE_HOST",
        "AOLKCANJCMJ": 4,
        "BKDENCDKDEE": "",
        "BPIIFMJLJAJ": [],
        "DAMGEPEMGNO": false,
        "DBACCKDPONG": [
          7525403,
          7525404
        ],
        "DIAFFIANKPH": false,
        "DKOMBMCJMMN": false,
        "EFBOKHEHKJM": [],
        "EIDINNIHMHD": false,
        "EKANPNMEFMG": [],
        "ENDBMMDPPAH": [],
        "FALLCBHGKON": "LOGIC_AND",
        "GEPGLHFDBNF": [],
        "GLJMLHNKKKO": "TALK_BEGIN_MANUAL",
        "HJFLPAICAEO": false,
        "HNFEAICLPLM": [],
        "HPPIPDNHFJG": false,
        "IBGGIIDBOAG": false,
        "IEFDIICFIJK": 752540603,
        "ILHDCGDKKKA": "TALK_HERO_LOCAL",
        "ILHDNJDDEOP": 7525406,
        "JGFEJPBPHGJ": [],
        "JNFAMBOFGHJ": false,
        "KINCAGMDMHH": [
          6512
        ],
        "KJLNGKKBBOI": "TALK_MARK_NONE",
        "KNBDEPPFNBN": 0,
        "LCIDOOMOIPM": 0,
        "LIJPPLJCHGI": 0,
        "LMAPLNHKPOH": [],
        "MBDOOOMPFCD": false,
        "MEGMNOELHAO": false,
        "MMCFFPNNDDP": false,
        "MOAKNHNKCON": 0,
        "MOFGBFLPGDM": [],
        "NGNGBPOHNJF": [
          {
            "_param": [
              "7525401",
              "2"
            ],
            "_type": "QUEST_COND_STATE_EQUAL"
          },
          {
            "_param": [
              "7525205",
              "3"
            ],
            "_type": "QUEST_COND_QUEST_STATE_NOT_EQUAL"
          }
        ],
        "NIJAPEJKLDI": false,
        "NMKNFLIHHHE": true,
        "NMMOKMEKDJO": false,
        "NPGONNBAOOI": 11675784845425773068,
        "OAIIIMFGNGM": false,
        "OAOCMNEPKOG": 75254,
        "ODEOIJMOMPL": [],
        "OMLNDCDBHEO": false,
        "PBFMFECIGDG": "TALK_NORMAL_QUEST",
        "PCCKKGAHFFJ": false,
        "PNACKFKJJHM": []
      },
      {
        "<DLGBBMLABOA>k__BackingField": 0,
        "ABDCADBLCFC": 0,
        "AIMIPKGBAHC": "",
        "ANDJNFLIDIJ": "PLAY_MODE_HOST",
        "AOLKCANJCMJ": 3,
        "BKDENCDKDEE": "",
        "BPIIFMJLJAJ": [],
        "DAMGEPEMGNO": false,
        "DBACCKDPONG": [
          7525403,
          7525404
        ],
        "DIAFFIANKPH": false,
        "DKOMBMCJMMN": false,
        "EFBOKHEHKJM": [],
        "EIDINNIHMHD": false,
        "EKANPNMEFMG": [],
        "ENDBMMDPPAH": [],
        "FALLCBHGKON": "LOGIC_NONE",
        "GEPGLHFDBNF": [],
        "GLJMLHNKKKO": "TALK_BEGIN_MANUAL",
        "HJFLPAICAEO": false,
        "HNFEAICLPLM": [],
        "HPPIPDNHFJG": false,
        "IBGGIIDBOAG": false,
        "IEFDIICFIJK": 752540703,
        "ILHDCGDKKKA": "TALK_HERO_LOCAL",
        "ILHDNJDDEOP": 7525407,
        "JGFEJPBPHGJ": [],
        "JNFAMBOFGHJ": false,
        "KINCAGMDMHH": [
          6512
        ],
        "KJLNGKKBBOI": "TALK_MARK_NONE",
        "KNBDEPPFNBN": 0,
        "LCIDOOMOIPM": 0,
        "LIJPPLJCHGI": 0,
        "LMAPLNHKPOH": [],
        "MBDOOOMPFCD": false,
        "MEGMNOELHAO": false,
        "MMCFFPNNDDP": false,
        "MOAKNHNKCON": 0,
        "MOFGBFLPGDM": [],
        "NGNGBPOHNJF": [
          {
            "_param": [
              "7525401",
              "2"
            ],
            "_type": "QUEST_COND_STATE_EQUAL"
          }
        ],
        "NIJAPEJKLDI": false,
        "NMKNFLIHHHE": true,
        "NMMOKMEKDJO": false,
        "NPGONNBAOOI": 17610978993433022278,
        "OAIIIMFGNGM": false,
        "OAOCMNEPKOG": 75254,
        "ODEOIJMOMPL": [],
        "OMLNDCDBHEO": false,
        "PBFMFECIGDG": "TALK_NORMAL_QUEST",
        "PCCKKGAHFFJ": false,
        "PNACKFKJJHM": []
      }
    ],
    "IBNCKLKHAKG": 0,
    "IEGCPJALJOA": 0,
    "IELNANBAMLH": "QUEST_PAUSE_RES_DESTROY_CLIENT_ONLY",
    "ILHDNJDDEOP": 75254,
    "ILICEMABDDI": [],
    "JAPLGJLDPHJ": [],
    "JDCIPCDDDPK": 0,
    "JDEFCNEDMLL": 0,
    "KCONOGOIGIH": 0,
    "LEFIHLHODBM": [],
    "LMCFKPMJGEO": false,
    "MEJIMPLKPHN": 0,
    "MHHFFHCLDKI": false,
    "MMOEEOFGHHG": 3250151839,
    "NJGLJLODPBN": false,
    "NKAKCKAJCLD": 0,
    "NOCNCPAGOPC": "Actor/Quest/WQ75254",
    "OPIDGNOCOHD": "QUEST_HIDDEN",
    "PAINLIBBLDK": "WQ",
    "PEDANLIDLGE": 0,
    "PEFIFLDHPEE": false,
    "PIGICJKACHG": [],
    "PPJLLGCPCOL": {
      "HDHKBHOLGIM": {}
    }
  },
  "meta": {
    "questType": "WQ",
    "series": 0,
    "mainQuestTag": "MAINQUEST_TAG_NONE",
    "showType": "QUEST_HIDDEN",
    "repeatable": false,
    "recommendLevel": 0,
    "chapterId": 0,
    "chapterTitle": "",
    "chapterNum": "",
    "needPlayerLevel": null,
    "cityId": null,
    "cityName": "",
    "unlockDesc": "",
    "preMainQuestIds": [],
    "nextMainQuestIds": [],
    "rewardIdList": [],
    "rewards": []
  }
}